{
  "zipcode": "75081",
  "total_listings": 87,
  "scraped_at": "2026-02-20 05:35:23",
  "listings": [
    {
      "zpid": "27175659",
      "price": 630000,
      "zestimate": 609300,
      "imgSrc": "https://photos.zillowstatic.com/fp/3805d79e26b65276e448ecd5284c0f40-p_e.jpg",
      "detailUrl": "https://www.zillow.com/homedetails/523-Stillmeadow-Dr-Richardson-TX-75081/27175659_zpid/",
      "statusText": "House for sale",
      "isZillowOwned": false,
      "addressRaw": "523 Stillmeadow Dr, Richardson, TX 75081",
      "streetAddress": "523 Stillmeadow Dr",
      "city": "Richardson",
      "state": "TX",
      "zipcode": "75081",
      "rentZestimate": 4068,
      "taxAssessedValue": 548810,
      "bedrooms": 6,
      "bathrooms": 4,
      "livingArea": 3687,
      "lotAreaValue": 9365.4,
      "homeType": "SINGLE_FAMILY",
      "homeStatus": "FOR_SALE",
      "daysOnZillow": 0,
      "timeOnZillow": 11838000,
      "latitude": 32.92798,
      "longitude": -96.72558,
      "isFeatured": false,
      "isPreforeclosureAuction": false,
      "country": "USA",
      "currency": "USD",
      "priceRaw": "$630,000"
    },
    {
      "zpid": "27162712",
      "price": 560000,
      "zestimate": 551500,
      "imgSrc": "https://photos.zillowstatic.com/fp/63fcd56dfe8989b7ebae476f50dd236b-p_e.jpg",
      "detailUrl": "https://www.zillow.com/homedetails/1-Spring-Valley-Ct-Richardson-TX-75081/27162712_zpid/",
      "statusText": "House for sale",
      "isZillowOwned": false,
      "addressRaw": "1 Spring Valley Ct, Richardson, TX 75081",
      "streetAddress": "1 Spring Valley Ct",
      "city": "Richardson",
      "state": "TX",
      "zipcode": "75081",
      "rentZestimate": 2896,
      "taxAssessedValue": 459260,
      "bedrooms": 4,
      "bathrooms": 3,
      "livingArea": 2521,
      "lotAreaValue": 0.328,
      "homeType": "SINGLE_FAMILY",
      "homeStatus": "FOR_SALE",
      "daysOnZillow": 89,
      "timeOnZillow": 7740040000,
      "latitude": 32.939392,
      "longitude": -96.71116,
      "priceChange": -10000,
      "datePriceChanged": 1770883200000,
      "isFeatured": false,
      "isPreforeclosureAuction": false,
      "country": "USA",
      "currency": "USD",
      "priceRaw": "$560,000"
    },
    {
      "zpid": "27159513",
      "price": 650000,
      "zestimate": 643500,
      "imgSrc": "https://photos.zillowstatic.com/fp/276d481673f3bbb5a6b059cbde3f82d2-p_e.jpg",
      "detailUrl": "https://www.zillow.com/homedetails/23-Grant-Cir-Richardson-TX-75081/27159513_zpid/",
      "statusText": "House for sale",
      "isZillowOwned": false,
      "addressRaw": "23 Grant Cir, Richardson, TX 75081",
      "streetAddress": "23 Grant Cir",
      "city": "Richardson",
      "state": "TX",
      "zipcode": "75081",
      "rentZestimate": 4100,
      "taxAssessedValue": 675070,
      "bedrooms": 5,
      "bathrooms": 6,
      "livingArea": 3604,
      "lotAreaValue": 8276.4,
      "homeType": "SINGLE_FAMILY",
      "homeStatus": "FOR_SALE",
      "daysOnZillow": 1,
      "timeOnZillow": 139647000,
      "latitude": 32.965126,
      "longitude": -96.693146,
      "isFeatured": false,
      "isPreforeclosureAuction": false,
      "country": "USA",
      "currency": "USD",
      "priceRaw": "$650,000"
    },
    {
      "zpid": "27160197",
      "price": 300000,
      "zestimate": 295700,
      "imgSrc": "https://photos.zillowstatic.com/fp/add90ee6cfbba0899d966cb7c33c636a-p_e.jpg",
      "detailUrl": "https://www.zillow.com/homedetails/1807-Eldora-Ct-Richardson-TX-75081/27160197_zpid/",
      "statusText": "House for sale",
      "isZillowOwned": false,
      "addressRaw": "1807 Eldora Ct, Richardson, TX 75081",
      "streetAddress": "1807 Eldora Ct",
      "city": "Richardson",
      "state": "TX",
      "zipcode": "75081",
      "rentZestimate": 2613,
      "taxAssessedValue": 382750,
      "bedrooms": 4,
      "bathrooms": 2,
      "livingArea": 1899,
      "lotAreaValue": 10236.6,
      "homeType": "SINGLE_FAMILY",
      "homeStatus": "FOR_SALE",
      "daysOnZillow": 175,
      "timeOnZillow": 15168186000,
      "latitude": 32.972946,
      "longitude": -96.69347,
      "isFeatured": false,
      "isPreforeclosureAuction": false,
      "country": "USA",
      "currency": "USD",
      "priceRaw": "$300,000"
    },
    {
      "zpid": "27177739",
      "price": 450000,
      "imgSrc": "https://photos.zillowstatic.com/fp/f5ccd2406b3f9bb98bebecb8d9f9d31e-p_e.jpg",
      "detailUrl": "https://www.zillow.com/homedetails/806-Westminster-Dr-Richardson-TX-75081/27177739_zpid/",
      "statusText": "House for sale",
      "isZillowOwned": false,
      "addressRaw": "806 Westminster Dr, Richardson, TX 75081",
      "streetAddress": "806 Westminster Dr",
      "city": "Richardson",
      "state": "TX",
      "zipcode": "75081",
      "taxAssessedValue": 423320,
      "bedrooms": 4,
      "bathrooms": 3,
      "livingArea": 2118,
      "lotAreaValue": 9408.96,
      "homeType": "SINGLE_FAMILY",
      "homeStatus": "FOR_SALE",
      "daysOnZillow": 28,
      "timeOnZillow": 2479447000,
      "latitude": 32.95909,
      "longitude": -96.68684,
      "isFeatured": false,
      "isPreforeclosureAuction": false,
      "country": "USA",
      "currency": "USD",
      "priceRaw": "$450,000"
    },
    {
      "zpid": "27162545",
      "price": 449000,
      "imgSrc": "https://photos.zillowstatic.com/fp/36af045ce81ffd5182085bd52d227d6b-p_e.jpg",
      "detailUrl": "https://www.zillow.com/homedetails/1105-E-Spring-Valley-Rd-Richardson-TX-75081/27162545_zpid/",
      "statusText": "House for sale",
      "isZillowOwned": false,
      "addressRaw": "1105 E Spring Valley Rd, Richardson, TX 75081",
      "streetAddress": "1105 E Spring Valley Rd",
      "city": "Richardson",
      "state": "TX",
      "zipcode": "75081",
      "taxAssessedValue": 478060,
      "bedrooms": 4,
      "bathrooms": 3,
      "livingArea": 2406,
      "lotAreaValue": 9757.44,
      "homeType": "SINGLE_FAMILY",
      "homeStatus": "FOR_SALE",
      "daysOnZillow": 69,
      "timeOnZillow": 6025512000,
      "latitude": 32.939014,
      "longitude": -96.70899,
      "priceChange": -16000,
      "datePriceChanged": 1771315200000,
      "isFeatured": false,
      "isPreforeclosureAuction": false,
      "country": "USA",
      "currency": "USD",
      "priceRaw": "$449,000"
    },
    {
      "zpid": "27178665",
      "price": 525000,
      "zestimate": 450800,
      "imgSrc": "https://photos.zillowstatic.com/fp/18c3cb0a2908302e44f6602c411f298f-p_e.jpg",
      "detailUrl": "https://www.zillow.com/homedetails/1708-Tulane-Dr-Richardson-TX-75081/27178665_zpid/",
      "statusText": "House for sale",
      "isZillowOwned": false,
      "addressRaw": "1708 Tulane Dr, Richardson, TX 75081",
      "streetAddress": "1708 Tulane Dr",
      "city": "Richardson",
      "state": "TX",
      "zipcode": "75081",
      "rentZestimate": 2811,
      "taxAssessedValue": 413510,
      "bedrooms": 4,
      "bathrooms": 3,
      "livingArea": 2592,
      "lotAreaValue": 9016.92,
      "homeType": "SINGLE_FAMILY",
      "homeStatus": "FOR_SALE",
      "daysOnZillow": 3,
      "timeOnZillow": 330951000,
      "latitude": 32.956326,
      "longitude": -96.69172,
      "isFeatured": false,
      "isPreforeclosureAuction": false,
      "country": "USA",
      "currency": "USD",
      "priceRaw": "$525,000"
    },
    {
      "zpid": "27178338",
      "price": 405000,
      "zestimate": 399100,
      "imgSrc": "https://photos.zillowstatic.com/fp/cb141480dbc2ed243944e38a367ce885-p_e.jpg",
      "detailUrl": "https://www.zillow.com/homedetails/1617-Baltimore-Dr-Richardson-TX-75081/27178338_zpid/",
      "statusText": "House for sale",
      "isZillowOwned": false,
      "addressRaw": "1617 Baltimore Dr, Richardson, TX 75081",
      "streetAddress": "1617 Baltimore Dr",
      "city": "Richardson",
      "state": "TX",
      "zipcode": "75081",
      "rentZestimate": 2344,
      "taxAssessedValue": 356560,
      "bedrooms": 4,
      "bathrooms": 2,
      "livingArea": 2103,
      "lotAreaValue": 9016.92,
      "homeType": "SINGLE_FAMILY",
      "homeStatus": "FOR_SALE",
      "daysOnZillow": 35,
      "timeOnZillow": 3091879000,
      "latitude": 32.93382,
      "longitude": -96.69308,
      "priceChange": -15000,
      "datePriceChanged": 1771228800000,
      "isFeatured": false,
      "isPreforeclosureAuction": false,
      "country": "USA",
      "currency": "USD",
      "priceRaw": "$405,000"
    },
    {
      "zpid": "27174856",
      "price": 299990,
      "zestimate": 292900,
      "imgSrc": "https://photos.zillowstatic.com/fp/6b82b233d8fe0474b634e41b57ca8e4b-p_e.jpg",
      "detailUrl": "https://www.zillow.com/homedetails/613-La-Salle-Dr-Richardson-TX-75081/27174856_zpid/",
      "statusText": "House for sale",
      "isZillowOwned": false,
      "addressRaw": "613 La Salle Dr, Richardson, TX 75081",
      "streetAddress": "613 La Salle Dr",
      "city": "Richardson",
      "state": "TX",
      "zipcode": "75081",
      "rentZestimate": 2047,
      "taxAssessedValue": 274710,
      "bedrooms": 3,
      "bathrooms": 2,
      "livingArea": 1138,
      "lotAreaValue": 8102.16,
      "homeType": "SINGLE_FAMILY",
      "homeStatus": "FOR_SALE",
      "daysOnZillow": 63,
      "timeOnZillow": 5524371000,
      "latitude": 32.951347,
      "longitude": -96.716606,
      "priceChange": -10010,
      "datePriceChanged": 1769068800000,
      "isFeatured": false,
      "isPreforeclosureAuction": false,
      "country": "USA",
      "currency": "USD",
      "priceRaw": "$299,990"
    },
    {
      "zpid": "27159523",
      "price": 475000,
      "imgSrc": "https://photos.zillowstatic.com/fp/bc8d630bb3ff5cbaab7017f3a9727303-p_e.jpg",
      "detailUrl": "https://www.zillow.com/homedetails/1411-N-Yale-Blvd-Richardson-TX-75081/27159523_zpid/",
      "statusText": "House for sale",
      "isZillowOwned": false,
      "addressRaw": "1411 N Yale Blvd, Richardson, TX 75081",
      "streetAddress": "1411 N Yale Blvd",
      "city": "Richardson",
      "state": "TX",
      "zipcode": "75081",
      "taxAssessedValue": 348450,
      "bedrooms": 4,
      "bathrooms": 3,
      "livingArea": 2522,
      "lotAreaValue": 0.258,
      "homeType": "SINGLE_FAMILY",
      "homeStatus": "FOR_SALE",
      "daysOnZillow": 18,
      "timeOnZillow": 1563815000,
      "latitude": 32.96554,
      "longitude": -96.692566,
      "isFeatured": false,
      "isPreforeclosureAuction": false,
      "country": "USA",
      "currency": "USD",
      "priceRaw": "$475,000"
    },
    {
      "zpid": "27162495",
      "price": 580000,
      "zestimate": 566000,
      "imgSrc": "https://photos.zillowstatic.com/fp/ab48f4e33dfcb242ac2b909c4852fed1-p_e.jpg",
      "detailUrl": "https://www.zillow.com/homedetails/1114-Rainbow-Dr-Richardson-TX-75081/27162495_zpid/",
      "statusText": "House for sale",
      "isZillowOwned": false,
      "addressRaw": "1114 Rainbow Dr, Richardson, TX 75081",
      "streetAddress": "1114 Rainbow Dr",
      "city": "Richardson",
      "state": "TX",
      "zipcode": "75081",
      "rentZestimate": 3416,
      "taxAssessedValue": 471120,
      "bedrooms": 4,
      "bathrooms": 3,
      "livingArea": 2705,
      "lotAreaValue": 9365.4,
      "homeType": "SINGLE_FAMILY",
      "homeStatus": "FOR_SALE",
      "daysOnZillow": 31,
      "timeOnZillow": 2741638000,
      "latitude": 32.94111,
      "longitude": -96.70781,
      "priceChange": -5000,
      "datePriceChanged": 1771401600000,
      "isFeatured": false,
      "isPreforeclosureAuction": false,
      "country": "USA",
      "currency": "USD",
      "priceRaw": "$580,000"
    },
    {
      "zpid": "27165236",
      "price": 485000,
      "imgSrc": "https://photos.zillowstatic.com/fp/7ef510e74a7b27404029e95514779e56-p_e.jpg",
      "detailUrl": "https://www.zillow.com/homedetails/504-Pittman-St-Richardson-TX-75081/27165236_zpid/",
      "statusText": "House for sale",
      "isZillowOwned": false,
      "addressRaw": "504 Pittman St, Richardson, TX 75081",
      "streetAddress": "504 Pittman St",
      "city": "Richardson",
      "state": "TX",
      "zipcode": "75081",
      "taxAssessedValue": 424580,
      "bedrooms": 3,
      "bathrooms": 2,
      "livingArea": 1773,
      "lotAreaValue": 0.35,
      "homeType": "SINGLE_FAMILY",
      "homeStatus": "FOR_SALE",
      "daysOnZillow": 6,
      "timeOnZillow": 596056000,
      "latitude": 32.942326,
      "longitude": -96.7247,
      "isFeatured": false,
      "isPreforeclosureAuction": false,
      "country": "USA",
      "currency": "USD",
      "priceRaw": "$485,000"
    },
    {
      "zpid": "27175473",
      "price": 369900,
      "zestimate": 365400,
      "imgSrc": "https://photos.zillowstatic.com/fp/77f9cbfcb3cd0831b5604457a1c1c7aa-p_e.jpg",
      "detailUrl": "https://www.zillow.com/homedetails/435-Tiffany-Trl-Richardson-TX-75081/27175473_zpid/",
      "statusText": "House for sale",
      "isZillowOwned": false,
      "addressRaw": "435 Tiffany Trl, Richardson, TX 75081",
      "streetAddress": "435 Tiffany Trl",
      "city": "Richardson",
      "state": "TX",
      "zipcode": "75081",
      "rentZestimate": 2286,
      "taxAssessedValue": 306000,
      "bedrooms": 3,
      "bathrooms": 2,
      "livingArea": 1815,
      "lotAreaValue": 5837.04,
      "homeType": "SINGLE_FAMILY",
      "homeStatus": "FOR_SALE",
      "daysOnZillow": 33,
      "timeOnZillow": 2928440000,
      "latitude": 32.92995,
      "longitude": -96.73133,
      "priceChange": -19100,
      "datePriceChanged": 1771142400000,
      "isFeatured": false,
      "isPreforeclosureAuction": false,
      "country": "USA",
      "currency": "USD",
      "priceRaw": "$369,900"
    },
    {
      "zpid": "27179509",
      "price": 399000,
      "imgSrc": "https://photos.zillowstatic.com/fp/329f1114212c4b1fcf3da2195a6b0990-p_e.jpg",
      "detailUrl": "https://www.zillow.com/homedetails/605-Spring-Valley-Rd-Richardson-TX-75081/27179509_zpid/",
      "statusText": "House for sale",
      "isZillowOwned": false,
      "addressRaw": "605 Spring Valley Rd, Richardson, TX 75081",
      "streetAddress": "605 Spring Valley Rd",
      "city": "Richardson",
      "state": "TX",
      "zipcode": "75081",
      "taxAssessedValue": 412300,
      "bedrooms": 4,
      "bathrooms": 3,
      "livingArea": 2339,
      "lotAreaValue": 9583.2,
      "homeType": "SINGLE_FAMILY",
      "homeStatus": "FOR_SALE",
      "daysOnZillow": 181,
      "timeOnZillow": 15700331000,
      "latitude": 32.94019,
      "longitude": -96.71715,
      "priceChange": -31000,
      "datePriceChanged": 1760770800000,
      "isFeatured": false,
      "isPreforeclosureAuction": false,
      "country": "USA",
      "currency": "USD",
      "priceRaw": "$399,000"
    },
    {
      "zpid": "27177192",
      "price": 444995,
      "zestimate": 435300,
      "imgSrc": "https://photos.zillowstatic.com/fp/7b39e9f3434a1ee23c4c0fe86c1a8e7d-p_e.jpg",
      "detailUrl": "https://www.zillow.com/homedetails/1603-University-Dr-Richardson-TX-75081/27177192_zpid/",
      "statusText": "House for sale",
      "isZillowOwned": false,
      "addressRaw": "1603 University Dr, Richardson, TX 75081",
      "streetAddress": "1603 University Dr",
      "city": "Richardson",
      "state": "TX",
      "zipcode": "75081",
      "rentZestimate": 3058,
      "taxAssessedValue": 440900,
      "bedrooms": 4,
      "bathrooms": 2,
      "livingArea": 2093,
      "lotAreaValue": 8624.88,
      "homeType": "SINGLE_FAMILY",
      "homeStatus": "FOR_SALE",
      "daysOnZillow": 2,
      "timeOnZillow": 191221000,
      "latitude": 32.946156,
      "longitude": -96.695114,
      "isFeatured": false,
      "isPreforeclosureAuction": false,
      "country": "USA",
      "currency": "USD",
      "priceRaw": "$444,995"
    },
    {
      "zpid": "27163933",
      "price": 281900,
      "zestimate": 276800,
      "imgSrc": "https://photos.zillowstatic.com/fp/b09a2f96713bc96614191cb7fece6a31-p_e.jpg",
      "detailUrl": "https://www.zillow.com/homedetails/1901-Baylor-Dr-Richardson-TX-75081/27163933_zpid/",
      "statusText": "House for sale",
      "isZillowOwned": false,
      "addressRaw": "1901 Baylor Dr, Richardson, TX 75081",
      "streetAddress": "1901 Baylor Dr",
      "city": "Richardson",
      "state": "TX",
      "zipcode": "75081",
      "rentZestimate": 2697,
      "taxAssessedValue": 372500,
      "bedrooms": 4,
      "bathrooms": 3,
      "livingArea": 1821,
      "lotAreaValue": 8755.56,
      "homeType": "SINGLE_FAMILY",
      "homeStatus": "FOR_SALE",
      "daysOnZillow": 21,
      "timeOnZillow": 1865164000,
      "latitude": 32.93207,
      "longitude": -96.68903,
      "isFeatured": false,
      "isPreforeclosureAuction": false,
      "country": "USA",
      "currency": "USD",
      "priceRaw": "$281,900"
    },
    {
      "zpid": "27176519",
      "price": 435000,
      "zestimate": 432500,
      "imgSrc": "https://photos.zillowstatic.com/fp/013ab6b83f6a6803befc74621f2662db-p_e.jpg",
      "detailUrl": "https://www.zillow.com/homedetails/2123-Sunrise-Trl-Richardson-TX-75081/27176519_zpid/",
      "statusText": "House for sale",
      "isZillowOwned": false,
      "addressRaw": "2123 Sunrise Trl, Richardson, TX 75081",
      "streetAddress": "2123 Sunrise Trl",
      "city": "Richardson",
      "state": "TX",
      "zipcode": "75081",
      "rentZestimate": 2511,
      "taxAssessedValue": 363010,
      "bedrooms": 4,
      "bathrooms": 2,
      "livingArea": 1845,
      "lotAreaValue": 7492.32,
      "homeType": "SINGLE_FAMILY",
      "homeStatus": "FOR_SALE",
      "daysOnZillow": 146,
      "timeOnZillow": 12647195000,
      "latitude": 32.940815,
      "longitude": -96.68409,
      "priceChange": -9000,
      "datePriceChanged": 1770796800000,
      "isFeatured": false,
      "isPreforeclosureAuction": false,
      "country": "USA",
      "currency": "USD",
      "priceRaw": "$435,000"
    },
    {
      "zpid": "27160408",
      "price": 495000,
      "zestimate": 494800,
      "imgSrc": "https://photos.zillowstatic.com/fp/4b0c5422cb20bcd0c5b5412c7c66f448-p_e.jpg",
      "detailUrl": "https://www.zillow.com/homedetails/1007-Harness-Ln-Richardson-TX-75081/27160408_zpid/",
      "statusText": "House for sale",
      "isZillowOwned": false,
      "addressRaw": "1007 Harness Ln, Richardson, TX 75081",
      "streetAddress": "1007 Harness Ln",
      "city": "Richardson",
      "state": "TX",
      "zipcode": "75081",
      "rentZestimate": 2788,
      "taxAssessedValue": 496420,
      "bedrooms": 4,
      "bathrooms": 3,
      "livingArea": 2479,
      "lotAreaValue": 7535.88,
      "homeType": "SINGLE_FAMILY",
      "homeStatus": "FOR_SALE",
      "daysOnZillow": 125,
      "timeOnZillow": 10865247000,
      "latitude": 32.961605,
      "longitude": -96.69681,
      "priceChange": -3500,
      "datePriceChanged": 1771488000000,
      "isFeatured": false,
      "isPreforeclosureAuction": false,
      "country": "USA",
      "currency": "USD",
      "priceRaw": "$495,000"
    },
    {
      "zpid": "27159726",
      "price": 479000,
      "zestimate": 476300,
      "imgSrc": "https://photos.zillowstatic.com/fp/6385a7f6a0f747f0fabf9d6a5631b19e-p_e.jpg",
      "detailUrl": "https://www.zillow.com/homedetails/1614-Aurora-Dr-Richardson-TX-75081/27159726_zpid/",
      "statusText": "House for sale",
      "isZillowOwned": false,
      "addressRaw": "1614 Aurora Dr, Richardson, TX 75081",
      "streetAddress": "1614 Aurora Dr",
      "city": "Richardson",
      "state": "TX",
      "zipcode": "75081",
      "rentZestimate": 3315,
      "taxAssessedValue": 500000,
      "bedrooms": 4,
      "bathrooms": 3,
      "livingArea": 2690,
      "lotAreaValue": 8973.36,
      "homeType": "SINGLE_FAMILY",
      "homeStatus": "FOR_SALE",
      "daysOnZillow": 225,
      "timeOnZillow": 19494546000,
      "latitude": 32.969097,
      "longitude": -96.69329,
      "priceChange": -500,
      "datePriceChanged": 1763539200000,
      "isFeatured": false,
      "isPreforeclosureAuction": false,
      "country": "USA",
      "currency": "USD",
      "priceRaw": "$479,000"
    },
    {
      "zpid": "27175237",
      "price": 405000,
      "zestimate": 388200,
      "imgSrc": "https://photos.zillowstatic.com/fp/932f9431a46f17ff4d41d412034c59ea-p_e.jpg",
      "detailUrl": "https://www.zillow.com/homedetails/433-Tall-Oaks-Ln-Richardson-TX-75081/27175237_zpid/",
      "statusText": "House for sale",
      "isZillowOwned": false,
      "addressRaw": "433 Tall Oaks Ln, Richardson, TX 75081",
      "streetAddress": "433 Tall Oaks Ln",
      "city": "Richardson",
      "state": "TX",
      "zipcode": "75081",
      "rentZestimate": 2286,
      "taxAssessedValue": 423010,
      "bedrooms": 3,
      "bathrooms": 2,
      "livingArea": 1950,
      "lotAreaValue": 5183.64,
      "homeType": "SINGLE_FAMILY",
      "homeStatus": "FOR_SALE",
      "daysOnZillow": 0,
      "timeOnZillow": 68577000,
      "latitude": 32.9276,
      "longitude": -96.7305,
      "isFeatured": false,
      "isPreforeclosureAuction": false,
      "country": "USA",
      "currency": "USD",
      "priceRaw": "$405,000"
    },
    {
      "zpid": "27178381",
      "price": 424900,
      "zestimate": 421100,
      "imgSrc": "https://photos.zillowstatic.com/fp/457bbc3b79ec69d9ebdce96ceac30911-p_e.jpg",
      "detailUrl": "https://www.zillow.com/homedetails/1700-Richland-Dr-Richardson-TX-75081/27178381_zpid/",
      "statusText": "House for sale",
      "isZillowOwned": false,
      "addressRaw": "1700 Richland Dr, Richardson, TX 75081",
      "streetAddress": "1700 Richland Dr",
      "city": "Richardson",
      "state": "TX",
      "zipcode": "75081",
      "rentZestimate": 2859,
      "taxAssessedValue": 380200,
      "bedrooms": 4,
      "bathrooms": 3,
      "livingArea": 2064,
      "lotAreaValue": 9234.72,
      "homeType": "SINGLE_FAMILY",
      "homeStatus": "FOR_SALE",
      "daysOnZillow": 118,
      "timeOnZillow": 10248085000,
      "latitude": 32.93247,
      "longitude": -96.692825,
      "priceChange": -14100,
      "datePriceChanged": 1768377600000,
      "isFeatured": false,
      "isPreforeclosureAuction": false,
      "country": "USA",
      "currency": "USD",
      "priceRaw": "$424,900"
    },
    {
      "zpid": "27177152",
      "price": 458000,
      "zestimate": 452000,
      "imgSrc": "https://photos.zillowstatic.com/fp/1561b3c6ec50d07600727a95af08820e-p_e.jpg",
      "detailUrl": "https://www.zillow.com/homedetails/1618-University-Dr-Richardson-TX-75081/27177152_zpid/",
      "statusText": "House for sale",
      "isZillowOwned": false,
      "addressRaw": "1618 University Dr, Richardson, TX 75081",
      "streetAddress": "1618 University Dr",
      "city": "Richardson",
      "state": "TX",
      "zipcode": "75081",
      "rentZestimate": 3850,
      "taxAssessedValue": 380040,
      "bedrooms": 4,
      "bathrooms": 3,
      "livingArea": 2132,
      "lotAreaValue": 8624.88,
      "homeType": "SINGLE_FAMILY",
      "homeStatus": "FOR_SALE",
      "daysOnZillow": 34,
      "timeOnZillow": 2981545000,
      "latitude": 32.945683,
      "longitude": -96.69324,
      "priceChange": -6900,
      "datePriceChanged": 1770710400000,
      "isFeatured": false,
      "isPreforeclosureAuction": false,
      "country": "USA",
      "currency": "USD",
      "priceRaw": "$458,000"
    },
    {
      "zpid": "27160170",
      "price": 375000,
      "zestimate": 370000,
      "imgSrc": "https://photos.zillowstatic.com/fp/9f98f574e6e967b1aa4e0c931f0f45ad-p_e.jpg",
      "detailUrl": "https://www.zillow.com/homedetails/1510-Stoneham-Pl-Richardson-TX-75081/27160170_zpid/",
      "statusText": "House for sale",
      "isZillowOwned": false,
      "addressRaw": "1510 Stoneham Pl, Richardson, TX 75081",
      "streetAddress": "1510 Stoneham Pl",
      "city": "Richardson",
      "state": "TX",
      "zipcode": "75081",
      "rentZestimate": 2554,
      "taxAssessedValue": 333360,
      "bedrooms": 4,
      "bathrooms": 3,
      "livingArea": 2229,
      "lotAreaValue": 6534,
      "homeType": "SINGLE_FAMILY",
      "homeStatus": "FOR_SALE",
      "daysOnZillow": 86,
      "timeOnZillow": 7491781000,
      "latitude": 32.97199,
      "longitude": -96.695564,
      "isFeatured": false,
      "isPreforeclosureAuction": false,
      "country": "USA",
      "currency": "USD",
      "priceRaw": "$375,000"
    },
    {
      "zpid": "27178330",
      "price": 439000,
      "zestimate": 431500,
      "imgSrc": "https://photos.zillowstatic.com/fp/2a49ee7e4e968e5b8a9e159a95180db5-p_e.jpg",
      "detailUrl": "https://www.zillow.com/homedetails/1715-Baltimore-Dr-Richardson-TX-75081/27178330_zpid/",
      "statusText": "House for sale",
      "isZillowOwned": false,
      "addressRaw": "1715 Baltimore Dr, Richardson, TX 75081",
      "streetAddress": "1715 Baltimore Dr",
      "city": "Richardson",
      "state": "TX",
      "zipcode": "75081",
      "rentZestimate": 3090,
      "taxAssessedValue": 428450,
      "bedrooms": 4,
      "bathrooms": 2,
      "livingArea": 1933,
      "lotAreaValue": 10018.8,
      "homeType": "SINGLE_FAMILY",
      "homeStatus": "FOR_SALE",
      "daysOnZillow": 7,
      "timeOnZillow": 674666000,
      "latitude": 32.933807,
      "longitude": -96.69117,
      "isFeatured": false,
      "isPreforeclosureAuction": false,
      "country": "USA",
      "currency": "USD",
      "priceRaw": "$439,000"
    },
    {
      "zpid": "27176081",
      "price": 489999,
      "zestimate": 483000,
      "imgSrc": "https://photos.zillowstatic.com/fp/330c93025a12624438342cc88513c80c-p_e.jpg",
      "detailUrl": "https://www.zillow.com/homedetails/607-Tiffany-Trl-Richardson-TX-75081/27176081_zpid/",
      "statusText": "House for sale",
      "isZillowOwned": false,
      "addressRaw": "607 Tiffany Trl, Richardson, TX 75081",
      "streetAddress": "607 Tiffany Trl",
      "city": "Richardson",
      "state": "TX",
      "zipcode": "75081",
      "rentZestimate": 3039,
      "taxAssessedValue": 400230,
      "bedrooms": 4,
      "bathrooms": 3,
      "livingArea": 2390,
      "lotAreaValue": 9539.64,
      "homeType": "SINGLE_FAMILY",
      "homeStatus": "FOR_SALE",
      "daysOnZillow": 101,
      "timeOnZillow": 8797300000,
      "latitude": 32.92966,
      "longitude": -96.72318,
      "priceChange": -25001,
      "datePriceChanged": 1770451200000,
      "isFeatured": false,
      "isPreforeclosureAuction": false,
      "country": "USA",
      "currency": "USD",
      "priceRaw": "$489,999"
    },
    {
      "zpid": "27162628",
      "price": 475000,
      "zestimate": 463000,
      "imgSrc": "https://photos.zillowstatic.com/fp/7a3e839fcc0e39a7923314548f0cd0b6-p_e.jpg",
      "detailUrl": "https://www.zillow.com/homedetails/902-Windsong-Trl-Richardson-TX-75081/27162628_zpid/",
      "statusText": "House for sale",
      "isZillowOwned": false,
      "addressRaw": "902 Windsong Trl, Richardson, TX 75081",
      "streetAddress": "902 Windsong Trl",
      "city": "Richardson",
      "state": "TX",
      "zipcode": "75081",
      "rentZestimate": 2562,
      "taxAssessedValue": 507590,
      "bedrooms": 3,
      "bathrooms": 2,
      "livingArea": 2314,
      "lotAreaValue": 9365.4,
      "homeType": "SINGLE_FAMILY",
      "homeStatus": "FOR_SALE",
      "daysOnZillow": 29,
      "timeOnZillow": 2563875000,
      "latitude": 32.94244,
      "longitude": -96.712,
      "priceChange": -2500,
      "datePriceChanged": 1770278400000,
      "isFeatured": false,
      "isPreforeclosureAuction": false,
      "country": "USA",
      "currency": "USD",
      "priceRaw": "$475,000"
    },
    {
      "zpid": "27164998",
      "price": 449000,
      "zestimate": 441000,
      "imgSrc": "https://photos.zillowstatic.com/fp/fb1bb2976d775f197eda7670ae70218c-p_e.jpg",
      "detailUrl": "https://www.zillow.com/homedetails/1609-Heather-Glen-Ct-Richardson-TX-75081/27164998_zpid/",
      "statusText": "House for sale",
      "isZillowOwned": false,
      "addressRaw": "1609 Heather Glen Ct, Richardson, TX 75081",
      "streetAddress": "1609 Heather Glen Ct",
      "city": "Richardson",
      "state": "TX",
      "zipcode": "75081",
      "rentZestimate": 2406,
      "taxAssessedValue": 367000,
      "bedrooms": 4,
      "bathrooms": 2,
      "livingArea": 2008,
      "lotAreaValue": 9147.6,
      "homeType": "SINGLE_FAMILY",
      "homeStatus": "FOR_SALE",
      "daysOnZillow": 7,
      "timeOnZillow": 650790000,
      "latitude": 32.96895,
      "longitude": -96.69839,
      "isFeatured": false,
      "isPreforeclosureAuction": false,
      "country": "USA",
      "currency": "USD",
      "priceRaw": "$449,000"
    },
    {
      "zpid": "80226787",
      "price": 357000,
      "zestimate": 353100,
      "imgSrc": "https://photos.zillowstatic.com/fp/84be7d6643ac0e0dbe8567e84b711ac4-p_e.jpg",
      "detailUrl": "https://www.zillow.com/homedetails/604-Gray-Stone-Ln-Richardson-TX-75081/80226787_zpid/",
      "statusText": "Townhouse for sale",
      "isZillowOwned": false,
      "addressRaw": "604 Gray Stone Ln, Richardson, TX 75081",
      "streetAddress": "604 Gray Stone Ln",
      "city": "Richardson",
      "state": "TX",
      "zipcode": "75081",
      "rentZestimate": 2685,
      "taxAssessedValue": 379420,
      "bedrooms": 3,
      "bathrooms": 3,
      "livingArea": 1755,
      "lotAreaValue": 2178,
      "homeType": "TOWNHOUSE",
      "homeStatus": "FOR_SALE",
      "daysOnZillow": 118,
      "timeOnZillow": 10262819000,
      "latitude": 32.947803,
      "longitude": -96.71769,
      "priceChange": -2900,
      "datePriceChanged": 1771401600000,
      "isFeatured": false,
      "isPreforeclosureAuction": false,
      "country": "USA",
      "currency": "USD",
      "priceRaw": "$357,000"
    },
    {
      "zpid": "27175969",
      "price": 485000,
      "zestimate": 471200,
      "imgSrc": "https://photos.zillowstatic.com/fp/bf8b25e435d8b753ea794b91a2edea24-p_e.jpg",
      "detailUrl": "https://www.zillow.com/homedetails/601-Fieldwood-Cir-Richardson-TX-75081/27175969_zpid/",
      "statusText": "House for sale",
      "isZillowOwned": false,
      "addressRaw": "601 Fieldwood Cir, Richardson, TX 75081",
      "streetAddress": "601 Fieldwood Cir",
      "city": "Richardson",
      "state": "TX",
      "zipcode": "75081",
      "rentZestimate": 3068,
      "taxAssessedValue": 440000,
      "bedrooms": 4,
      "bathrooms": 3,
      "livingArea": 2475,
      "lotAreaValue": 10628.64,
      "homeType": "SINGLE_FAMILY",
      "homeStatus": "FOR_SALE",
      "daysOnZillow": 13,
      "timeOnZillow": 1180693000,
      "latitude": 32.9323,
      "longitude": -96.723885,
      "isFeatured": false,
      "isPreforeclosureAuction": false,
      "country": "USA",
      "currency": "USD",
      "priceRaw": "$485,000"
    },
    {
      "zpid": "27175714",
      "price": 565000,
      "imgSrc": "https://photos.zillowstatic.com/fp/5a384c6c1bdddbf7bdafe3f388825840-p_e.jpg",
      "detailUrl": "https://www.zillow.com/homedetails/526-Goodwin-Dr-Richardson-TX-75081/27175714_zpid/",
      "statusText": "House for sale",
      "isZillowOwned": false,
      "addressRaw": "526 Goodwin Dr, Richardson, TX 75081",
      "streetAddress": "526 Goodwin Dr",
      "city": "Richardson",
      "state": "TX",
      "zipcode": "75081",
      "taxAssessedValue": 469910,
      "bedrooms": 4,
      "bathrooms": 3,
      "livingArea": 2655,
      "lotAreaValue": 9365.4,
      "homeType": "SINGLE_FAMILY",
      "homeStatus": "FOR_SALE",
      "daysOnZillow": 10,
      "timeOnZillow": 922470000,
      "latitude": 32.92663,
      "longitude": -96.72522,
      "isFeatured": false,
      "isPreforeclosureAuction": false,
      "country": "USA",
      "currency": "USD",
      "priceRaw": "$565,000"
    },
    {
      "zpid": "27160101",
      "price": 490000,
      "imgSrc": "https://photos.zillowstatic.com/fp/25db78e1ef1f095c2eb8792e511bfb07-p_e.jpg",
      "detailUrl": "https://www.zillow.com/homedetails/1704-Elk-Grove-Dr-Richardson-TX-75081/27160101_zpid/",
      "statusText": "House for sale",
      "isZillowOwned": false,
      "addressRaw": "1704 Elk Grove Dr, Richardson, TX 75081",
      "streetAddress": "1704 Elk Grove Dr",
      "city": "Richardson",
      "state": "TX",
      "zipcode": "75081",
      "taxAssessedValue": 458040,
      "bedrooms": 4,
      "bathrooms": 3,
      "livingArea": 2344,
      "lotAreaValue": 7710.12,
      "homeType": "SINGLE_FAMILY",
      "homeStatus": "FOR_SALE",
      "daysOnZillow": 105,
      "timeOnZillow": 9123150000,
      "latitude": 32.96931,
      "longitude": -96.68601,
      "priceChange": -5000,
      "datePriceChanged": 1769068800000,
      "isFeatured": false,
      "isPreforeclosureAuction": false,
      "country": "USA",
      "currency": "USD",
      "priceRaw": "$490,000"
    },
    {
      "zpid": "27162001",
      "price": 430000,
      "imgSrc": "https://photos.zillowstatic.com/fp/204c8c61c5fe3b682b3a0b97d9bae3c8-p_e.jpg",
      "detailUrl": "https://www.zillow.com/homedetails/909-Hillsdale-Dr-Richardson-TX-75081/27162001_zpid/",
      "statusText": "House for sale",
      "isZillowOwned": false,
      "addressRaw": "909 Hillsdale Dr, Richardson, TX 75081",
      "streetAddress": "909 Hillsdale Dr",
      "city": "Richardson",
      "state": "TX",
      "zipcode": "75081",
      "taxAssessedValue": 353200,
      "bedrooms": 4,
      "bathrooms": 2,
      "livingArea": 2112,
      "lotAreaValue": 9147.6,
      "homeType": "SINGLE_FAMILY",
      "homeStatus": "FOR_SALE",
      "daysOnZillow": 6,
      "timeOnZillow": 540542000,
      "latitude": 32.937847,
      "longitude": -96.709045,
      "isFeatured": false,
      "isPreforeclosureAuction": false,
      "country": "USA",
      "currency": "USD",
      "priceRaw": "$430,000"
    },
    {
      "zpid": "27160676",
      "price": 459000,
      "zestimate": 444600,
      "imgSrc": "https://photos.zillowstatic.com/fp/c3cfa75709fe34c5f6c830db6a7288c8-p_e.jpg",
      "detailUrl": "https://www.zillow.com/homedetails/528-Shirley-Ct-Richardson-TX-75081/27160676_zpid/",
      "statusText": "House for sale",
      "isZillowOwned": false,
      "addressRaw": "528 Shirley Ct, Richardson, TX 75081",
      "streetAddress": "528 Shirley Ct",
      "city": "Richardson",
      "state": "TX",
      "zipcode": "75081",
      "rentZestimate": 2933,
      "taxAssessedValue": 340000,
      "bedrooms": 3,
      "bathrooms": 3,
      "livingArea": 1884,
      "lotAreaValue": 9452.52,
      "homeType": "SINGLE_FAMILY",
      "homeStatus": "FOR_SALE",
      "daysOnZillow": 9,
      "timeOnZillow": 837813000,
      "latitude": 32.94429,
      "longitude": -96.72068,
      "isFeatured": false,
      "isPreforeclosureAuction": false,
      "country": "USA",
      "currency": "USD",
      "priceRaw": "$459,000"
    },
    {
      "zpid": "27163285",
      "price": 315000,
      "zestimate": 308300,
      "imgSrc": "https://photos.zillowstatic.com/fp/7fa90fcd0881342e54194bc9c10289fe-p_e.jpg",
      "detailUrl": "https://www.zillow.com/homedetails/1147-Shadyglen-Cir-Richardson-TX-75081/27163285_zpid/",
      "statusText": "House for sale",
      "isZillowOwned": false,
      "addressRaw": "1147 Shadyglen Cir, Richardson, TX 75081",
      "streetAddress": "1147 Shadyglen Cir",
      "city": "Richardson",
      "state": "TX",
      "zipcode": "75081",
      "rentZestimate": 2113,
      "taxAssessedValue": 275000,
      "bedrooms": 3,
      "bathrooms": 2,
      "livingArea": 1270,
      "lotAreaValue": 7492.32,
      "homeType": "SINGLE_FAMILY",
      "homeStatus": "FOR_SALE",
      "daysOnZillow": 154,
      "timeOnZillow": 13306746000,
      "latitude": 32.946095,
      "longitude": -96.706184,
      "isFeatured": false,
      "isPreforeclosureAuction": false,
      "country": "USA",
      "currency": "USD",
      "priceRaw": "$315,000"
    },
    {
      "zpid": "27177187",
      "price": 530000,
      "zestimate": 516000,
      "imgSrc": "https://photos.zillowstatic.com/fp/784ed197f1d53f62fdaf32fb475dbb3c-p_e.jpg",
      "detailUrl": "https://www.zillow.com/homedetails/1613-University-Dr-Richardson-TX-75081/27177187_zpid/",
      "statusText": "House for sale",
      "isZillowOwned": false,
      "addressRaw": "1613 University Dr, Richardson, TX 75081",
      "streetAddress": "1613 University Dr",
      "city": "Richardson",
      "state": "TX",
      "zipcode": "75081",
      "rentZestimate": 2888,
      "taxAssessedValue": 376960,
      "bedrooms": 4,
      "bathrooms": 2,
      "livingArea": 2278,
      "lotAreaValue": 8637.948,
      "homeType": "SINGLE_FAMILY",
      "homeStatus": "FOR_SALE",
      "daysOnZillow": 36,
      "timeOnZillow": 3126789000,
      "latitude": 32.94615,
      "longitude": -96.69395,
      "isFeatured": false,
      "isPreforeclosureAuction": false,
      "country": "USA",
      "currency": "USD",
      "priceRaw": "$530,000"
    },
    {
      "zpid": "27163636",
      "price": 370000,
      "imgSrc": "https://photos.zillowstatic.com/fp/fa840b00b5e6ebc6d447eddb11b6459c-p_e.jpg",
      "detailUrl": "https://www.zillow.com/homedetails/1127-Southwestern-Dr-Richardson-TX-75081/27163636_zpid/",
      "statusText": "House for sale",
      "isZillowOwned": false,
      "addressRaw": "1127 Southwestern Dr, Richardson, TX 75081",
      "streetAddress": "1127 Southwestern Dr",
      "city": "Richardson",
      "state": "TX",
      "zipcode": "75081",
      "taxAssessedValue": 347930,
      "bedrooms": 3,
      "bathrooms": 2,
      "livingArea": 1610,
      "lotAreaValue": 8123.94,
      "homeType": "SINGLE_FAMILY",
      "homeStatus": "FOR_SALE",
      "daysOnZillow": 29,
      "timeOnZillow": 2552435000,
      "latitude": 32.951347,
      "longitude": -96.70718,
      "priceChange": -4000,
      "datePriceChanged": 1770883200000,
      "isFeatured": false,
      "isPreforeclosureAuction": false,
      "country": "USA",
      "currency": "USD",
      "priceRaw": "$370,000"
    },
    {
      "zpid": "27175677",
      "price": 519900,
      "zestimate": 510300,
      "imgSrc": "https://photos.zillowstatic.com/fp/66b6b3b910e64a52cd8e230825b49a35-p_e.jpg",
      "detailUrl": "https://www.zillow.com/homedetails/512-Stillmeadow-Dr-Richardson-TX-75081/27175677_zpid/",
      "statusText": "House for sale",
      "isZillowOwned": false,
      "addressRaw": "512 Stillmeadow Dr, Richardson, TX 75081",
      "streetAddress": "512 Stillmeadow Dr",
      "city": "Richardson",
      "state": "TX",
      "zipcode": "75081",
      "rentZestimate": 4237,
      "taxAssessedValue": 472690,
      "bedrooms": 4,
      "bathrooms": 3,
      "livingArea": 2416,
      "lotAreaValue": 9016.92,
      "homeType": "SINGLE_FAMILY",
      "homeStatus": "FOR_SALE",
      "daysOnZillow": 41,
      "timeOnZillow": 3623037000,
      "latitude": 32.927498,
      "longitude": -96.72685,
      "priceChange": -5000,
      "datePriceChanged": 1770451200000,
      "isFeatured": false,
      "isPreforeclosureAuction": false,
      "country": "USA",
      "currency": "USD",
      "priceRaw": "$519,900"
    },
    {
      "zpid": "27165426",
      "price": 475000,
      "zestimate": 459200,
      "imgSrc": "https://photos.zillowstatic.com/fp/e870612974d5e41054dda85a3cbf4669-p_e.jpg",
      "detailUrl": "https://www.zillow.com/homedetails/531-Summit-Dr-Richardson-TX-75081/27165426_zpid/",
      "statusText": "House for sale",
      "isZillowOwned": false,
      "addressRaw": "531 Summit Dr, Richardson, TX 75081",
      "streetAddress": "531 Summit Dr",
      "city": "Richardson",
      "state": "TX",
      "zipcode": "75081",
      "rentZestimate": 2685,
      "taxAssessedValue": 411330,
      "bedrooms": 4,
      "bathrooms": 3,
      "livingArea": 2051,
      "lotAreaValue": 0.257,
      "homeType": "SINGLE_FAMILY",
      "homeStatus": "FOR_SALE",
      "daysOnZillow": 70,
      "timeOnZillow": 6108555000,
      "latitude": 32.93923,
      "longitude": -96.72131,
      "isFeatured": false,
      "isPreforeclosureAuction": false,
      "country": "USA",
      "currency": "USD",
      "priceRaw": "$475,000"
    },
    {
      "zpid": "27175838",
      "price": 469000,
      "zestimate": 462000,
      "imgSrc": "https://photos.zillowstatic.com/fp/46797614e4f51ef7cec25ae270b4ca7a-p_e.jpg",
      "detailUrl": "https://www.zillow.com/homedetails/602-Wentworth-Dr-Richardson-TX-75081/27175838_zpid/",
      "statusText": "House for sale",
      "isZillowOwned": false,
      "addressRaw": "602 Wentworth Dr, Richardson, TX 75081",
      "streetAddress": "602 Wentworth Dr",
      "city": "Richardson",
      "state": "TX",
      "zipcode": "75081",
      "rentZestimate": 3527,
      "taxAssessedValue": 452700,
      "bedrooms": 5,
      "bathrooms": 3,
      "livingArea": 2402,
      "lotAreaValue": 9901.188,
      "homeType": "SINGLE_FAMILY",
      "homeStatus": "FOR_SALE",
      "daysOnZillow": 37,
      "timeOnZillow": 3263246000,
      "latitude": 32.92568,
      "longitude": -96.723564,
      "priceChange": -6000,
      "datePriceChanged": 1770364800000,
      "isFeatured": false,
      "isPreforeclosureAuction": false,
      "country": "USA",
      "currency": "USD",
      "priceRaw": "$469,000"
    },
    {
      "zpid": "27169403",
      "price": 430000,
      "zestimate": 421300,
      "imgSrc": "https://photos.zillowstatic.com/fp/9ea550dbad93b0d847dee0f3db2832a1-p_e.jpg",
      "detailUrl": "https://www.zillow.com/homedetails/1103-Larkspur-Dr-Richardson-TX-75081/27169403_zpid/",
      "statusText": "House for sale",
      "isZillowOwned": false,
      "addressRaw": "1103 Larkspur Dr, Richardson, TX 75081",
      "streetAddress": "1103 Larkspur Dr",
      "city": "Richardson",
      "state": "TX",
      "zipcode": "75081",
      "rentZestimate": 2480,
      "taxAssessedValue": 273000,
      "bedrooms": 3,
      "bathrooms": 2,
      "livingArea": 1694,
      "lotAreaValue": 8407.08,
      "homeType": "SINGLE_FAMILY",
      "homeStatus": "FOR_SALE",
      "daysOnZillow": 64,
      "timeOnZillow": 5606007000,
      "latitude": 32.94897,
      "longitude": -96.70852,
      "priceChange": -15000,
      "datePriceChanged": 1768377600000,
      "isFeatured": false,
      "isPreforeclosureAuction": false,
      "country": "USA",
      "currency": "USD",
      "priceRaw": "$430,000"
    },
    {
      "zpid": "27162231",
      "price": 469000,
      "zestimate": 466300,
      "imgSrc": "https://photos.zillowstatic.com/fp/26e6514e3a53c6cace6ae4c238cd0c9d-p_e.jpg",
      "detailUrl": "https://www.zillow.com/homedetails/900-E-Berkeley-Dr-Richardson-TX-75081/27162231_zpid/",
      "statusText": "House for sale",
      "isZillowOwned": false,
      "addressRaw": "900 E Berkeley Dr, Richardson, TX 75081",
      "streetAddress": "900 E Berkeley Dr",
      "city": "Richardson",
      "state": "TX",
      "zipcode": "75081",
      "rentZestimate": 3064,
      "taxAssessedValue": 400190,
      "bedrooms": 4,
      "bathrooms": 3,
      "livingArea": 2121,
      "lotAreaValue": 0.272,
      "homeType": "SINGLE_FAMILY",
      "homeStatus": "FOR_SALE",
      "daysOnZillow": 162,
      "timeOnZillow": 14052266000,
      "latitude": 32.935646,
      "longitude": -96.71175,
      "priceChange": -10000,
      "datePriceChanged": 1767945600000,
      "isFeatured": false,
      "isPreforeclosureAuction": false,
      "country": "USA",
      "currency": "USD",
      "priceRaw": "$469,000"
    },
    {
      "zpid": "27177311",
      "price": 499900,
      "zestimate": 488400,
      "imgSrc": "https://photos.zillowstatic.com/fp/b9b4fa81ab1bd6ea178793d05f89dfc8-p_e.jpg",
      "detailUrl": "https://www.zillow.com/homedetails/314-Amherst-Ave-Richardson-TX-75081/27177311_zpid/",
      "statusText": "House for sale",
      "isZillowOwned": false,
      "addressRaw": "314 Amherst Ave, Richardson, TX 75081",
      "streetAddress": "314 Amherst Ave",
      "city": "Richardson",
      "state": "TX",
      "zipcode": "75081",
      "rentZestimate": 3508,
      "taxAssessedValue": 452080,
      "bedrooms": 3,
      "bathrooms": 3,
      "livingArea": 2707,
      "lotAreaValue": 10497.96,
      "homeType": "SINGLE_FAMILY",
      "homeStatus": "FOR_SALE",
      "daysOnZillow": 21,
      "timeOnZillow": 1863624000,
      "latitude": 32.95223,
      "longitude": -96.69283,
      "isFeatured": false,
      "isPreforeclosureAuction": false,
      "country": "USA",
      "currency": "USD",
      "priceRaw": "$499,900"
    },
    {
      "zpid": "27162076",
      "price": 539000,
      "imgSrc": "https://photos.zillowstatic.com/fp/df5033acb04965a63d9313c33a03a06f-p_e.jpg",
      "detailUrl": "https://www.zillow.com/homedetails/914-Edgewood-Dr-Richardson-TX-75081/27162076_zpid/",
      "statusText": "House for sale",
      "isZillowOwned": false,
      "addressRaw": "914 Edgewood Dr, Richardson, TX 75081",
      "streetAddress": "914 Edgewood Dr",
      "city": "Richardson",
      "state": "TX",
      "zipcode": "75081",
      "taxAssessedValue": 508430,
      "bedrooms": 4,
      "bathrooms": 3,
      "livingArea": 2169,
      "lotAreaValue": 9147.6,
      "homeType": "SINGLE_FAMILY",
      "homeStatus": "FOR_SALE",
      "daysOnZillow": 174,
      "timeOnZillow": 15109031000,
      "latitude": 32.935616,
      "longitude": -96.70847,
      "priceChange": -10900,
      "datePriceChanged": 1768204800000,
      "isFeatured": false,
      "isPreforeclosureAuction": false,
      "country": "USA",
      "currency": "USD",
      "priceRaw": "$539,000"
    },
    {
      "zpid": "303901486",
      "price": 729900,
      "zestimate": 722300,
      "imgSrc": "https://photos.zillowstatic.com/fp/cd24fbf93788a4cee5b957caf6a7655f-p_e.jpg",
      "detailUrl": "https://www.zillow.com/homedetails/912-Banyan-Tree-Ln-Richardson-TX-75081/303901486_zpid/",
      "statusText": "House for sale",
      "isZillowOwned": false,
      "addressRaw": "912 Banyan Tree Ln, Richardson, TX 75081",
      "streetAddress": "912 Banyan Tree Ln",
      "city": "Richardson",
      "state": "TX",
      "zipcode": "75081",
      "rentZestimate": 4621,
      "taxAssessedValue": 796000,
      "bedrooms": 4,
      "bathrooms": 4,
      "livingArea": 3387,
      "lotAreaValue": 4312.44,
      "homeType": "SINGLE_FAMILY",
      "homeStatus": "FOR_SALE",
      "daysOnZillow": 169,
      "timeOnZillow": 14683448000,
      "latitude": 32.93612,
      "longitude": -96.73294,
      "priceChange": -20000,
      "datePriceChanged": 1770624000000,
      "isFeatured": false,
      "isPreforeclosureAuction": false,
      "country": "USA",
      "currency": "USD",
      "priceRaw": "$729,900"
    },
    {
      "zpid": "96496770",
      "price": 320000,
      "zestimate": 315800,
      "imgSrc": "https://photos.zillowstatic.com/fp/d4c646d151f5d0b72b20aafc2a1f5ead-p_e.jpg",
      "detailUrl": "https://www.zillow.com/homedetails/611-Matthew-Pl-Richardson-TX-75081/96496770_zpid/",
      "statusText": "Townhouse for sale",
      "isZillowOwned": false,
      "addressRaw": "611 Matthew Pl, Richardson, TX 75081",
      "streetAddress": "611 Matthew Pl",
      "city": "Richardson",
      "state": "TX",
      "zipcode": "75081",
      "rentZestimate": 2528,
      "taxAssessedValue": 412030,
      "bedrooms": 3,
      "bathrooms": 3,
      "livingArea": 1669,
      "lotAreaValue": 1873.08,
      "homeType": "TOWNHOUSE",
      "homeStatus": "FOR_SALE",
      "daysOnZillow": 78,
      "timeOnZillow": 6790978000,
      "latitude": 32.942642,
      "longitude": -96.73325,
      "isFeatured": false,
      "isPreforeclosureAuction": false,
      "country": "USA",
      "currency": "USD",
      "priceRaw": "$320,000"
    },
    {
      "zpid": "27164106",
      "price": 385000,
      "zestimate": 377400,
      "imgSrc": "https://photos.zillowstatic.com/fp/c140aee76c32f7057155ce24eb70f08b-p_e.jpg",
      "detailUrl": "https://www.zillow.com/homedetails/5-Green-View-Cir-Richardson-TX-75081/27164106_zpid/",
      "statusText": "House for sale",
      "isZillowOwned": false,
      "addressRaw": "5 Green View Cir, Richardson, TX 75081",
      "streetAddress": "5 Green View Cir",
      "city": "Richardson",
      "state": "TX",
      "zipcode": "75081",
      "rentZestimate": 2163,
      "taxAssessedValue": 340030,
      "bedrooms": 3,
      "bathrooms": 2,
      "livingArea": 1474,
      "lotAreaValue": 8407.08,
      "homeType": "SINGLE_FAMILY",
      "homeStatus": "FOR_SALE",
      "daysOnZillow": 41,
      "timeOnZillow": 3621226000,
      "latitude": 32.93706,
      "longitude": -96.68854,
      "isFeatured": false,
      "isPreforeclosureAuction": false,
      "country": "USA",
      "currency": "USD",
      "priceRaw": "$385,000"
    },
    {
      "zpid": "27169265",
      "price": 449900,
      "zestimate": 439500,
      "imgSrc": "https://photos.zillowstatic.com/fp/461dfbb754017732176e7c00a2939a31-p_e.jpg",
      "detailUrl": "https://www.zillow.com/homedetails/103-Wake-Dr-Richardson-TX-75081/27169265_zpid/",
      "statusText": "House for sale",
      "isZillowOwned": false,
      "addressRaw": "103 Wake Dr, Richardson, TX 75081",
      "streetAddress": "103 Wake Dr",
      "city": "Richardson",
      "state": "TX",
      "zipcode": "75081",
      "rentZestimate": 2764,
      "taxAssessedValue": 362080,
      "bedrooms": 5,
      "bathrooms": 2,
      "livingArea": 2150,
      "lotAreaValue": 9104.04,
      "homeType": "SINGLE_FAMILY",
      "homeStatus": "FOR_SALE",
      "daysOnZillow": 11,
      "timeOnZillow": 964457000,
      "latitude": 32.94809,
      "longitude": -96.71204,
      "isFeatured": false,
      "isPreforeclosureAuction": false,
      "country": "USA",
      "currency": "USD",
      "priceRaw": "$449,900"
    },
    {
      "zpid": "27177147",
      "price": 429995,
      "zestimate": 425500,
      "imgSrc": "https://photos.zillowstatic.com/fp/eb09771a827c5030cafec0792f1e5b78-p_e.jpg",
      "detailUrl": "https://www.zillow.com/homedetails/1608-University-Dr-Richardson-TX-75081/27177147_zpid/",
      "statusText": "House for sale",
      "isZillowOwned": false,
      "addressRaw": "1608 University Dr, Richardson, TX 75081",
      "streetAddress": "1608 University Dr",
      "city": "Richardson",
      "state": "TX",
      "zipcode": "75081",
      "rentZestimate": 3160,
      "taxAssessedValue": 399200,
      "bedrooms": 4,
      "bathrooms": 3,
      "livingArea": 1999,
      "lotAreaValue": 8624.88,
      "homeType": "SINGLE_FAMILY",
      "homeStatus": "FOR_SALE",
      "daysOnZillow": 17,
      "timeOnZillow": 1486876000,
      "latitude": 32.945686,
      "longitude": -96.69441,
      "priceChange": -50000,
      "datePriceChanged": 1771315200000,
      "isFeatured": false,
      "isPreforeclosureAuction": false,
      "country": "USA",
      "currency": "USD",
      "priceRaw": "$429,995"
    },
    {
      "zpid": "27162289",
      "price": 472000,
      "zestimate": 468900,
      "imgSrc": "https://photos.zillowstatic.com/fp/380b3a016d9277df99c169eb9e90a64f-p_e.jpg",
      "detailUrl": "https://www.zillow.com/homedetails/1109-E-Berkeley-Dr-Richardson-TX-75081/27162289_zpid/",
      "statusText": "House for sale",
      "isZillowOwned": false,
      "addressRaw": "1109 E Berkeley Dr, Richardson, TX 75081",
      "streetAddress": "1109 E Berkeley Dr",
      "city": "Richardson",
      "state": "TX",
      "zipcode": "75081",
      "rentZestimate": 2424,
      "taxAssessedValue": 397880,
      "bedrooms": 4,
      "bathrooms": 2,
      "livingArea": 2091,
      "lotAreaValue": 9496.08,
      "homeType": "SINGLE_FAMILY",
      "homeStatus": "FOR_SALE",
      "daysOnZillow": 94,
      "timeOnZillow": 8148193000,
      "latitude": 32.93239,
      "longitude": -96.70601,
      "priceChange": -5300,
      "datePriceChanged": 1770364800000,
      "isFeatured": false,
      "isPreforeclosureAuction": false,
      "country": "USA",
      "currency": "USD",
      "priceRaw": "$472,000"
    },
    {
      "zpid": "27163715",
      "price": 370000,
      "zestimate": 362400,
      "imgSrc": "https://photos.zillowstatic.com/fp/1620b076f4ed5673b08a5c313bf02650-p_e.jpg",
      "detailUrl": "https://www.zillow.com/homedetails/1121-Midway-Dr-Richardson-TX-75081/27163715_zpid/",
      "statusText": "House for sale",
      "isZillowOwned": false,
      "addressRaw": "1121 Midway Dr, Richardson, TX 75081",
      "streetAddress": "1121 Midway Dr",
      "city": "Richardson",
      "state": "TX",
      "zipcode": "75081",
      "rentZestimate": 2183,
      "taxAssessedValue": 359030,
      "bedrooms": 3,
      "bathrooms": 2,
      "livingArea": 1372,
      "lotAreaValue": 8581.32,
      "homeType": "SINGLE_FAMILY",
      "homeStatus": "FOR_SALE",
      "daysOnZillow": 31,
      "timeOnZillow": 2736804000,
      "latitude": 32.953087,
      "longitude": -96.70868,
      "isFeatured": false,
      "isPreforeclosureAuction": false,
      "country": "USA",
      "currency": "USD",
      "priceRaw": "$370,000"
    },
    {
      "zpid": "27165992",
      "price": 385000,
      "imgSrc": "https://photos.zillowstatic.com/fp/376ca32f192eaffe07cbd14ff608e26f-p_e.jpg",
      "detailUrl": "https://www.zillow.com/homedetails/1804-University-Dr-Richardson-TX-75081/27165992_zpid/",
      "statusText": "House for sale",
      "isZillowOwned": false,
      "addressRaw": "1804 University Dr, Richardson, TX 75081",
      "streetAddress": "1804 University Dr",
      "city": "Richardson",
      "state": "TX",
      "zipcode": "75081",
      "taxAssessedValue": 360320,
      "bedrooms": 4,
      "bathrooms": 3,
      "livingArea": 1921,
      "lotAreaValue": 8407.08,
      "homeType": "SINGLE_FAMILY",
      "homeStatus": "FOR_SALE",
      "daysOnZillow": 35,
      "timeOnZillow": 3094056000,
      "latitude": 32.94566,
      "longitude": -96.69056,
      "priceChange": -5000,
      "datePriceChanged": 1770019200000,
      "isFeatured": false,
      "isPreforeclosureAuction": false,
      "country": "USA",
      "currency": "USD",
      "priceRaw": "$385,000"
    },
    {
      "zpid": "27166428",
      "price": 365000,
      "zestimate": 357400,
      "imgSrc": "https://photos.zillowstatic.com/fp/ffb2246f7fff28d8accd9b20e173c00b-p_e.jpg",
      "detailUrl": "https://www.zillow.com/homedetails/316-Hillside-Ave-Richardson-TX-75081/27166428_zpid/",
      "statusText": "House for sale",
      "isZillowOwned": false,
      "addressRaw": "316 Hillside Ave, Richardson, TX 75081",
      "streetAddress": "316 Hillside Ave",
      "city": "Richardson",
      "state": "TX",
      "zipcode": "75081",
      "rentZestimate": 2305,
      "taxAssessedValue": 296590,
      "bedrooms": 3,
      "bathrooms": 2,
      "livingArea": 1198,
      "lotAreaValue": 0.313,
      "homeType": "SINGLE_FAMILY",
      "homeStatus": "FOR_SALE",
      "daysOnZillow": 151,
      "timeOnZillow": 13070831000,
      "latitude": 32.956436,
      "longitude": -96.7247,
      "priceChange": -34999,
      "datePriceChanged": 1767600000000,
      "isFeatured": false,
      "isPreforeclosureAuction": false,
      "country": "USA",
      "currency": "USD",
      "priceRaw": "$365,000"
    },
    {
      "zpid": "27179644",
      "price": 239900,
      "zestimate": 232700,
      "imgSrc": "https://photos.zillowstatic.com/fp/4757a5e60be2172fbb0ddcf22d52590f-p_e.jpg",
      "detailUrl": "https://www.zillow.com/homedetails/513-Towne-House-Ln-Richardson-TX-75081/27179644_zpid/",
      "statusText": "Townhouse for sale",
      "isZillowOwned": false,
      "addressRaw": "513 Towne House Ln, Richardson, TX 75081",
      "streetAddress": "513 Towne House Ln",
      "city": "Richardson",
      "state": "TX",
      "zipcode": "75081",
      "rentZestimate": 2252,
      "taxAssessedValue": 229820,
      "bedrooms": 3,
      "bathrooms": 3,
      "livingArea": 1817,
      "lotAreaValue": 2744.28,
      "homeType": "TOWNHOUSE",
      "homeStatus": "FOR_SALE",
      "daysOnZillow": 23,
      "timeOnZillow": 2036357000,
      "latitude": 32.94215,
      "longitude": -96.71482,
      "isFeatured": false,
      "isPreforeclosureAuction": false,
      "country": "USA",
      "currency": "USD",
      "priceRaw": "$239,900"
    },
    {
      "zpid": "96524834",
      "price": 355000,
      "zestimate": 348000,
      "imgSrc": "https://photos.zillowstatic.com/fp/ce8caa272451f44b5da1923a4e01c9d4-p_e.jpg",
      "detailUrl": "https://www.zillow.com/homedetails/736-S-Greenville-Ave-Richardson-TX-75081/96524834_zpid/",
      "statusText": "Townhouse for sale",
      "isZillowOwned": false,
      "addressRaw": "736 S Greenville Ave, Richardson, TX 75081",
      "streetAddress": "736 S Greenville Ave",
      "city": "Richardson",
      "state": "TX",
      "zipcode": "75081",
      "rentZestimate": 2112,
      "taxAssessedValue": 345660,
      "bedrooms": 2,
      "bathrooms": 3,
      "livingArea": 1301,
      "homeType": "TOWNHOUSE",
      "homeStatus": "FOR_SALE",
      "daysOnZillow": 13,
      "timeOnZillow": 1192043000,
      "latitude": 32.940865,
      "longitude": -96.73356,
      "isFeatured": false,
      "isPreforeclosureAuction": false,
      "country": "USA",
      "currency": "USD",
      "priceRaw": "$355,000"
    },
    {
      "zpid": "27179638",
      "price": 260000,
      "zestimate": 253700,
      "imgSrc": "https://photos.zillowstatic.com/fp/66dd4e22c87fa53bfdb00df5304c31ed-p_e.jpg",
      "detailUrl": "https://www.zillow.com/homedetails/525-Towne-House-Ln-Richardson-TX-75081/27179638_zpid/",
      "statusText": "Townhouse for sale",
      "isZillowOwned": false,
      "addressRaw": "525 Towne House Ln, Richardson, TX 75081",
      "streetAddress": "525 Towne House Ln",
      "city": "Richardson",
      "state": "TX",
      "zipcode": "75081",
      "rentZestimate": 2152,
      "taxAssessedValue": 248820,
      "bedrooms": 3,
      "bathrooms": 3,
      "livingArea": 1606,
      "lotAreaValue": 2744.28,
      "homeType": "TOWNHOUSE",
      "homeStatus": "FOR_SALE",
      "daysOnZillow": 68,
      "timeOnZillow": 5954010000,
      "latitude": 32.94171,
      "longitude": -96.71477,
      "priceChange": -9000,
      "datePriceChanged": 1770105600000,
      "isFeatured": false,
      "isPreforeclosureAuction": false,
      "country": "USA",
      "currency": "USD",
      "priceRaw": "$260,000"
    },
    {
      "zpid": "27162673",
      "price": 539900,
      "zestimate": 530500,
      "imgSrc": "https://photos.zillowstatic.com/fp/8670a5df89368be6e0f00e610ba29a28-p_e.jpg",
      "detailUrl": "https://www.zillow.com/homedetails/1001-Morningstar-Trl-Richardson-TX-75081/27162673_zpid/",
      "statusText": "House for sale",
      "isZillowOwned": false,
      "addressRaw": "1001 Morningstar Trl, Richardson, TX 75081",
      "streetAddress": "1001 Morningstar Trl",
      "city": "Richardson",
      "state": "TX",
      "zipcode": "75081",
      "rentZestimate": 3169,
      "taxAssessedValue": 504350,
      "bedrooms": 4,
      "bathrooms": 3,
      "livingArea": 2048,
      "lotAreaValue": 10105.92,
      "homeType": "SINGLE_FAMILY",
      "homeStatus": "FOR_SALE",
      "daysOnZillow": 170,
      "timeOnZillow": 14741591000,
      "latitude": 32.940884,
      "longitude": -96.71104,
      "priceChange": -15100,
      "datePriceChanged": 1768809600000,
      "isFeatured": false,
      "isPreforeclosureAuction": false,
      "country": "USA",
      "currency": "USD",
      "priceRaw": "$539,900"
    },
    {
      "zpid": "27159822",
      "price": 460000,
      "imgSrc": "https://photos.zillowstatic.com/fp/3a648bd80058c23f37246a11ef12b7db-p_e.jpg",
      "detailUrl": "https://www.zillow.com/homedetails/1901-Forestwood-Dr-Richardson-TX-75081/27159822_zpid/",
      "statusText": "House for sale",
      "isZillowOwned": false,
      "addressRaw": "1901 Forestwood Dr, Richardson, TX 75081",
      "streetAddress": "1901 Forestwood Dr",
      "city": "Richardson",
      "state": "TX",
      "zipcode": "75081",
      "taxAssessedValue": 403410,
      "bedrooms": 4,
      "bathrooms": 2,
      "livingArea": 2165,
      "lotAreaValue": 9147.6,
      "homeType": "SINGLE_FAMILY",
      "homeStatus": "FOR_SALE",
      "daysOnZillow": 75,
      "timeOnZillow": 6530845000,
      "latitude": 32.96814,
      "longitude": -96.6904,
      "isFeatured": false,
      "isPreforeclosureAuction": false,
      "country": "USA",
      "currency": "USD",
      "priceRaw": "$460,000"
    },
    {
      "zpid": "27179635",
      "price": 299000,
      "imgSrc": "https://photos.zillowstatic.com/fp/b9bd4382c12d1bc221f6b61d2f009867-p_e.jpg",
      "detailUrl": "https://www.zillow.com/homedetails/531-Towne-House-Ln-Richardson-TX-75081/27179635_zpid/",
      "statusText": "Townhouse for sale",
      "isZillowOwned": false,
      "addressRaw": "531 Towne House Ln, Richardson, TX 75081",
      "streetAddress": "531 Towne House Ln",
      "city": "Richardson",
      "state": "TX",
      "zipcode": "75081",
      "taxAssessedValue": 293440,
      "bedrooms": 4,
      "bathrooms": 3,
      "livingArea": 1889,
      "lotAreaValue": 2744.28,
      "homeType": "TOWNHOUSE",
      "homeStatus": "FOR_SALE",
      "daysOnZillow": 35,
      "timeOnZillow": 3055529000,
      "latitude": 32.941517,
      "longitude": -96.714745,
      "isFeatured": false,
      "isPreforeclosureAuction": false,
      "country": "USA",
      "currency": "USD",
      "priceRaw": "$299,000"
    },
    {
      "zpid": "27160660",
      "price": 449000,
      "zestimate": 433600,
      "imgSrc": "https://photos.zillowstatic.com/fp/f76112a34a963206389ac0cfd35e6a5f-p_e.jpg",
      "detailUrl": "https://www.zillow.com/homedetails/310-S-Grove-Rd-Richardson-TX-75081/27160660_zpid/",
      "statusText": "House for sale",
      "isZillowOwned": false,
      "addressRaw": "310 S Grove Rd, Richardson, TX 75081",
      "streetAddress": "310 S Grove Rd",
      "city": "Richardson",
      "state": "TX",
      "zipcode": "75081",
      "rentZestimate": 2595,
      "taxAssessedValue": 353380,
      "bedrooms": 3,
      "bathrooms": 3,
      "livingArea": 2043,
      "lotAreaValue": 0.344,
      "homeType": "SINGLE_FAMILY",
      "homeStatus": "FOR_SALE",
      "daysOnZillow": 30,
      "timeOnZillow": 2642819000,
      "latitude": 32.944206,
      "longitude": -96.71845,
      "isFeatured": false,
      "isPreforeclosureAuction": false,
      "country": "USA",
      "currency": "USD",
      "priceRaw": "$449,000"
    },
    {
      "zpid": "27179637",
      "price": 260000,
      "zestimate": 252400,
      "imgSrc": "https://photos.zillowstatic.com/fp/81c093ab48cad39033d6102cdb4b6458-p_e.jpg",
      "detailUrl": "https://www.zillow.com/homedetails/527-Towne-House-Ln-Richardson-TX-75081/27179637_zpid/",
      "statusText": "Townhouse for sale",
      "isZillowOwned": false,
      "addressRaw": "527 Towne House Ln, Richardson, TX 75081",
      "streetAddress": "527 Towne House Ln",
      "city": "Richardson",
      "state": "TX",
      "zipcode": "75081",
      "rentZestimate": 2263,
      "taxAssessedValue": 249470,
      "bedrooms": 3,
      "bathrooms": 3,
      "livingArea": 1817,
      "lotAreaValue": 2744.28,
      "homeType": "TOWNHOUSE",
      "homeStatus": "FOR_SALE",
      "daysOnZillow": 72,
      "timeOnZillow": 6259928000,
      "latitude": 32.941647,
      "longitude": -96.71476,
      "isFeatured": false,
      "isPreforeclosureAuction": false,
      "country": "USA",
      "currency": "USD",
      "priceRaw": "$260,000"
    },
    {
      "zpid": "27164136",
      "price": 410000,
      "zestimate": 403100,
      "imgSrc": "https://photos.zillowstatic.com/fp/9e58becf7755fd66222d34d7580ad568-p_e.jpg",
      "detailUrl": "https://www.zillow.com/homedetails/2011-Clearfield-Cir-Richardson-TX-75081/27164136_zpid/",
      "statusText": "House for sale",
      "isZillowOwned": false,
      "addressRaw": "2011 Clearfield Cir, Richardson, TX 75081",
      "streetAddress": "2011 Clearfield Cir",
      "city": "Richardson",
      "state": "TX",
      "zipcode": "75081",
      "rentZestimate": 2181,
      "taxAssessedValue": 352660,
      "bedrooms": 4,
      "bathrooms": 2,
      "livingArea": 1862,
      "lotAreaValue": 8407.08,
      "homeType": "SINGLE_FAMILY",
      "homeStatus": "FOR_SALE",
      "daysOnZillow": 27,
      "timeOnZillow": 2393985000,
      "latitude": 32.93742,
      "longitude": -96.68453,
      "isFeatured": false,
      "isPreforeclosureAuction": false,
      "country": "USA",
      "currency": "USD",
      "priceRaw": "$410,000"
    },
    {
      "zpid": "27162539",
      "price": 510000,
      "zestimate": 493100,
      "imgSrc": "https://photos.zillowstatic.com/fp/7588fa23f7288700e616c36852871942-p_e.jpg",
      "detailUrl": "https://www.zillow.com/homedetails/1117-E-Spring-Valley-Rd-Richardson-TX-75081/27162539_zpid/",
      "statusText": "House for sale",
      "isZillowOwned": false,
      "addressRaw": "1117 E Spring Valley Rd, Richardson, TX 75081",
      "streetAddress": "1117 E Spring Valley Rd",
      "city": "Richardson",
      "state": "TX",
      "zipcode": "75081",
      "rentZestimate": 3110,
      "taxAssessedValue": 497920,
      "bedrooms": 4,
      "bathrooms": 3,
      "livingArea": 2778,
      "lotAreaValue": 10149.48,
      "homeType": "SINGLE_FAMILY",
      "homeStatus": "FOR_SALE",
      "daysOnZillow": 21,
      "timeOnZillow": 1856614000,
      "latitude": 32.938972,
      "longitude": -96.707535,
      "isFeatured": false,
      "isPreforeclosureAuction": false,
      "country": "USA",
      "currency": "USD",
      "priceRaw": "$510,000"
    },
    {
      "zpid": "303906326",
      "price": 709900,
      "imgSrc": "https://photos.zillowstatic.com/fp/dfc8216f8500819edae19ceb03f5d5cc-p_e.jpg",
      "detailUrl": "https://www.zillow.com/homedetails/911-Banyan-Tree-Ln-Richardson-TX-75081/303906326_zpid/",
      "statusText": "House for sale",
      "isZillowOwned": false,
      "addressRaw": "911 Banyan Tree Ln, Richardson, TX 75081",
      "streetAddress": "911 Banyan Tree Ln",
      "city": "Richardson",
      "state": "TX",
      "zipcode": "75081",
      "rentZestimate": 4469,
      "taxAssessedValue": 530000,
      "bedrooms": 4,
      "bathrooms": 4,
      "livingArea": 3382,
      "lotAreaValue": 3615.48,
      "homeType": "SINGLE_FAMILY",
      "homeStatus": "FOR_SALE",
      "daysOnZillow": 31,
      "timeOnZillow": 2726653000,
      "latitude": 32.93597,
      "longitude": -96.73261,
      "isFeatured": false,
      "isPreforeclosureAuction": false,
      "country": "USA",
      "currency": "USD",
      "priceRaw": "$709,900"
    },
    {
      "zpid": "27165427",
      "price": 385000,
      "zestimate": 376500,
      "imgSrc": "https://photos.zillowstatic.com/fp/6d909b0d87f6313c17b5ae17c2ea2918-p_e.jpg",
      "detailUrl": "https://www.zillow.com/homedetails/529-Summit-Dr-Richardson-TX-75081/27165427_zpid/",
      "statusText": "House for sale",
      "isZillowOwned": false,
      "addressRaw": "529 Summit Dr, Richardson, TX 75081",
      "streetAddress": "529 Summit Dr",
      "city": "Richardson",
      "state": "TX",
      "zipcode": "75081",
      "rentZestimate": 2178,
      "taxAssessedValue": 395530,
      "bedrooms": 3,
      "bathrooms": 2,
      "livingArea": 1698,
      "lotAreaValue": 9844.56,
      "homeType": "SINGLE_FAMILY",
      "homeStatus": "FOR_SALE",
      "daysOnZillow": 36,
      "timeOnZillow": 3186249000,
      "latitude": 32.93923,
      "longitude": -96.721565,
      "priceChange": -5000,
      "datePriceChanged": 1770883200000,
      "isFeatured": false,
      "isPreforeclosureAuction": false,
      "country": "USA",
      "currency": "USD",
      "priceRaw": "$385,000"
    },
    {
      "zpid": "27177954",
      "price": 410000,
      "zestimate": 402400,
      "imgSrc": "https://photos.zillowstatic.com/fp/0a3033ed8a4d9e117abd15d294aef8cc-p_e.jpg",
      "detailUrl": "https://www.zillow.com/homedetails/1908-Clemson-Dr-Richardson-TX-75081/27177954_zpid/",
      "statusText": "House for sale",
      "isZillowOwned": false,
      "addressRaw": "1908 Clemson Dr, Richardson, TX 75081",
      "streetAddress": "1908 Clemson Dr",
      "city": "Richardson",
      "state": "TX",
      "zipcode": "75081",
      "rentZestimate": 2675,
      "taxAssessedValue": 366570,
      "bedrooms": 3,
      "bathrooms": 2,
      "livingArea": 1794,
      "lotAreaValue": 9365.4,
      "homeType": "SINGLE_FAMILY",
      "homeStatus": "FOR_SALE",
      "daysOnZillow": 44,
      "timeOnZillow": 3871535000,
      "latitude": 32.96356,
      "longitude": -96.68797,
      "isFeatured": false,
      "isPreforeclosureAuction": false,
      "country": "USA",
      "currency": "USD",
      "priceRaw": "$410,000"
    },
    {
      "zpid": "27179566",
      "price": 465000,
      "zestimate": 454500,
      "imgSrc": "https://photos.zillowstatic.com/fp/1a0d5b68bbc7157ba1beec4afd946697-p_e.jpg",
      "detailUrl": "https://www.zillow.com/homedetails/307-S-Grove-Rd-Richardson-TX-75081/27179566_zpid/",
      "statusText": "House for sale",
      "isZillowOwned": false,
      "addressRaw": "307 S Grove Rd, Richardson, TX 75081",
      "streetAddress": "307 S Grove Rd",
      "city": "Richardson",
      "state": "TX",
      "zipcode": "75081",
      "rentZestimate": 3061,
      "taxAssessedValue": 412720,
      "bedrooms": 5,
      "bathrooms": 3,
      "livingArea": 2282,
      "lotAreaValue": 9452.52,
      "homeType": "SINGLE_FAMILY",
      "homeStatus": "FOR_SALE",
      "daysOnZillow": 86,
      "timeOnZillow": 7505185000,
      "latitude": 32.944607,
      "longitude": -96.71774,
      "priceChange": -10000,
      "datePriceChanged": 1767600000000,
      "isFeatured": false,
      "isPreforeclosureAuction": false,
      "country": "USA",
      "currency": "USD",
      "priceRaw": "$465,000"
    },
    {
      "zpid": "27164125",
      "price": 399900,
      "zestimate": 396100,
      "imgSrc": "https://photos.zillowstatic.com/fp/56f1e8d686e8648d7b239b336fa0d1c3-p_e.jpg",
      "detailUrl": "https://www.zillow.com/homedetails/32-Green-View-Cir-Richardson-TX-75081/27164125_zpid/",
      "statusText": "House for sale",
      "isZillowOwned": false,
      "addressRaw": "32 Green View Cir, Richardson, TX 75081",
      "streetAddress": "32 Green View Cir",
      "city": "Richardson",
      "state": "TX",
      "zipcode": "75081",
      "rentZestimate": 2601,
      "taxAssessedValue": 338740,
      "bedrooms": 5,
      "bathrooms": 2,
      "livingArea": 1859,
      "lotAreaValue": 0.299,
      "homeType": "SINGLE_FAMILY",
      "homeStatus": "FOR_SALE",
      "daysOnZillow": 105,
      "timeOnZillow": 9090672000,
      "latitude": 32.93713,
      "longitude": -96.687355,
      "priceChange": -25090,
      "datePriceChanged": 1771488000000,
      "isFeatured": false,
      "isPreforeclosureAuction": false,
      "country": "USA",
      "currency": "USD",
      "priceRaw": "$399,900"
    },
    {
      "zpid": "27179718",
      "price": 395000,
      "zestimate": 388100,
      "imgSrc": "https://photos.zillowstatic.com/fp/b8eb53dbdafdb40d9cd175d2f9fd5238-p_e.jpg",
      "detailUrl": "https://www.zillow.com/homedetails/1007-Elk-Grove-Dr-Richardson-TX-75081/27179718_zpid/",
      "statusText": "House for sale",
      "isZillowOwned": false,
      "addressRaw": "1007 Elk Grove Dr, Richardson, TX 75081",
      "streetAddress": "1007 Elk Grove Dr",
      "city": "Richardson",
      "state": "TX",
      "zipcode": "75081",
      "rentZestimate": 2363,
      "taxAssessedValue": 380940,
      "bedrooms": 3,
      "bathrooms": 2,
      "livingArea": 1695,
      "lotAreaValue": 7840.8,
      "homeType": "SINGLE_FAMILY",
      "homeStatus": "FOR_SALE",
      "daysOnZillow": 14,
      "timeOnZillow": 1276865000,
      "latitude": 32.960884,
      "longitude": -96.686386,
      "isFeatured": false,
      "isPreforeclosureAuction": false,
      "country": "USA",
      "currency": "USD",
      "priceRaw": "$395,000"
    },
    {
      "zpid": "27160487",
      "price": 420000,
      "zestimate": 403800,
      "imgSrc": "https://photos.zillowstatic.com/fp/cc53d0544246dec407b8281efc051eba-p_e.jpg",
      "detailUrl": "https://www.zillow.com/homedetails/203-Abrams-Rd-Richardson-TX-75081/27160487_zpid/",
      "statusText": "House for sale",
      "isZillowOwned": false,
      "addressRaw": "203 Abrams Rd, Richardson, TX 75081",
      "streetAddress": "203 Abrams Rd",
      "city": "Richardson",
      "state": "TX",
      "zipcode": "75081",
      "rentZestimate": 2217,
      "taxAssessedValue": 324710,
      "bedrooms": 3,
      "bathrooms": 2,
      "livingArea": 1806,
      "lotAreaValue": 0.256,
      "homeType": "SINGLE_FAMILY",
      "homeStatus": "FOR_SALE",
      "daysOnZillow": 24,
      "timeOnZillow": 2124936000,
      "latitude": 32.94684,
      "longitude": -96.72746,
      "isFeatured": false,
      "isPreforeclosureAuction": false,
      "country": "USA",
      "currency": "USD",
      "priceRaw": "$420,000"
    },
    {
      "zpid": "453028206",
      "price": 620000,
      "imgSrc": "https://photos.zillowstatic.com/fp/618e1b7a94189aa887852295d5ab9f94-p_e.jpg",
      "detailUrl": "https://www.zillow.com/homedetails/100-Trellis-Pl-102-Richardson-TX-75081/453028206_zpid/",
      "statusText": "House for sale",
      "isZillowOwned": false,
      "addressRaw": "100 Trellis Pl #102, Richardson, TX 75081",
      "streetAddress": "100 Trellis Pl #102",
      "city": "Richardson",
      "state": "TX",
      "zipcode": "75081",
      "rentZestimate": 3922,
      "bedrooms": 6,
      "bathrooms": 6,
      "livingArea": 3513,
      "lotAreaValue": 0.29,
      "homeType": "SINGLE_FAMILY",
      "homeStatus": "FOR_SALE",
      "daysOnZillow": 257,
      "timeOnZillow": 22268152000,
      "latitude": 32.945038,
      "longitude": -96.68607,
      "priceChange": -30000,
      "datePriceChanged": 1758006000000,
      "isFeatured": false,
      "isPreforeclosureAuction": false,
      "country": "USA",
      "currency": "USD",
      "priceRaw": "$620,000"
    },
    {
      "zpid": "27159512",
      "price": 449900,
      "zestimate": 446000,
      "imgSrc": "https://photos.zillowstatic.com/fp/901f792255b393c76394513bb01db464-p_e.jpg",
      "detailUrl": "https://www.zillow.com/homedetails/21-Grant-Cir-Richardson-TX-75081/27159512_zpid/",
      "statusText": "House for sale",
      "isZillowOwned": false,
      "addressRaw": "21 Grant Cir, Richardson, TX 75081",
      "streetAddress": "21 Grant Cir",
      "city": "Richardson",
      "state": "TX",
      "zipcode": "75081",
      "rentZestimate": 2748,
      "taxAssessedValue": 371150,
      "bedrooms": 5,
      "bathrooms": 3,
      "livingArea": 1986,
      "lotAreaValue": 9888.12,
      "homeType": "SINGLE_FAMILY",
      "homeStatus": "FOR_SALE",
      "daysOnZillow": 177,
      "timeOnZillow": 15326265000,
      "latitude": 32.9651,
      "longitude": -96.69345,
      "priceChange": -19100,
      "datePriceChanged": 1770710400000,
      "isFeatured": false,
      "isPreforeclosureAuction": false,
      "country": "USA",
      "currency": "USD",
      "priceRaw": "$449,900"
    },
    {
      "zpid": "27165134",
      "price": 350000,
      "zestimate": 338500,
      "imgSrc": "https://maps.googleapis.com/maps/api/staticmap?mobile=false&sensor=true&maptype=satellite&size=575x242&zoom=17&center=32.943389892578125,-96.72689056396484&key=AIzaSyBWYJWCA8FNMQvSe_k3LKfDGJaEgdKwsco&signature=Rxps55FNqBF3LQfLh1GL3_4rh4M=",
      "detailUrl": "https://www.zillow.com/homedetails/446-Highland-Blvd-Richardson-TX-75081/27165134_zpid/",
      "statusText": "House for sale",
      "isZillowOwned": false,
      "addressRaw": "446 Highland Blvd, Richardson, TX 75081",
      "streetAddress": "446 Highland Blvd",
      "city": "Richardson",
      "state": "TX",
      "zipcode": "75081",
      "rentZestimate": 2209,
      "taxAssessedValue": 248220,
      "bedrooms": 4,
      "bathrooms": 2,
      "livingArea": 1052,
      "lotAreaValue": 0.27599999999999997,
      "homeType": "SINGLE_FAMILY",
      "homeStatus": "FOR_SALE",
      "daysOnZillow": 53,
      "timeOnZillow": 4605091000,
      "latitude": 32.94339,
      "longitude": -96.72689,
      "isFeatured": false,
      "isPreforeclosureAuction": false,
      "country": "USA",
      "currency": "USD",
      "priceRaw": "$350,000"
    },
    {
      "zpid": "27177321",
      "price": 430000,
      "zestimate": 421300,
      "imgSrc": "https://photos.zillowstatic.com/fp/98ea8db982e9303d7775998c1c5b7cd4-p_e.jpg",
      "detailUrl": "https://www.zillow.com/homedetails/7-Yale-Cir-Richardson-TX-75081/27177321_zpid/",
      "statusText": "House for sale",
      "isZillowOwned": false,
      "addressRaw": "7 Yale Cir, Richardson, TX 75081",
      "streetAddress": "7 Yale Cir",
      "city": "Richardson",
      "state": "TX",
      "zipcode": "75081",
      "rentZestimate": 2903,
      "taxAssessedValue": 370410,
      "bedrooms": 4,
      "bathrooms": 2,
      "livingArea": 2010,
      "lotAreaValue": 0.257,
      "homeType": "SINGLE_FAMILY",
      "homeStatus": "FOR_SALE",
      "daysOnZillow": 18,
      "timeOnZillow": 1573511000,
      "latitude": 32.95092,
      "longitude": -96.691826,
      "priceChange": -15300,
      "datePriceChanged": 1769932800000,
      "isFeatured": false,
      "isPreforeclosureAuction": false,
      "country": "USA",
      "currency": "USD",
      "priceRaw": "$430,000"
    },
    {
      "zpid": "162815967",
      "price": 485000,
      "zestimate": 477500,
      "imgSrc": "https://photos.zillowstatic.com/fp/69107ca1e0c9da62d80c746e2c5b102f-p_e.jpg",
      "detailUrl": "https://www.zillow.com/homedetails/828-Rohan-Dr-Richardson-TX-75081/162815967_zpid/",
      "statusText": "Townhouse for sale",
      "isZillowOwned": false,
      "addressRaw": "828 Rohan Dr, Richardson, TX 75081",
      "streetAddress": "828 Rohan Dr",
      "city": "Richardson",
      "state": "TX",
      "zipcode": "75081",
      "rentZestimate": 2504,
      "taxAssessedValue": 469240,
      "bedrooms": 3,
      "bathrooms": 3,
      "livingArea": 1887,
      "lotAreaValue": 2003.76,
      "homeType": "TOWNHOUSE",
      "homeStatus": "FOR_SALE",
      "daysOnZillow": 41,
      "timeOnZillow": 3608663000,
      "latitude": 32.937317,
      "longitude": -96.72426,
      "priceChange": -10000,
      "datePriceChanged": 1770710400000,
      "isFeatured": false,
      "isPreforeclosureAuction": false,
      "country": "USA",
      "currency": "USD",
      "priceRaw": "$485,000"
    },
    {
      "zpid": "162814983",
      "price": 465000,
      "zestimate": 456600,
      "imgSrc": "https://photos.zillowstatic.com/fp/f365d7d46f06de4e10869bc307d2f51f-p_e.jpg",
      "detailUrl": "https://www.zillow.com/homedetails/869-Rohan-Dr-Richardson-TX-75081/162814983_zpid/",
      "statusText": "Townhouse for sale",
      "isZillowOwned": false,
      "addressRaw": "869 Rohan Dr, Richardson, TX 75081",
      "streetAddress": "869 Rohan Dr",
      "city": "Richardson",
      "state": "TX",
      "zipcode": "75081",
      "rentZestimate": 2525,
      "taxAssessedValue": 467570,
      "bedrooms": 3,
      "bathrooms": 3,
      "livingArea": 1938,
      "lotAreaValue": 2482.92,
      "homeType": "TOWNHOUSE",
      "homeStatus": "FOR_SALE",
      "daysOnZillow": 13,
      "timeOnZillow": 1172010000,
      "latitude": 32.936607,
      "longitude": -96.72382,
      "isFeatured": false,
      "isPreforeclosureAuction": false,
      "country": "USA",
      "currency": "USD",
      "priceRaw": "$465,000"
    },
    {
      "zpid": "460198442",
      "price": 225000,
      "zestimate": 218100,
      "imgSrc": "https://photos.zillowstatic.com/fp/a849a9a228acddd3f19cffeeebe535b4-p_e.jpg",
      "detailUrl": "https://www.zillow.com/homedetails/137-Trellis-Pl-Richardson-TX-75081/460198442_zpid/",
      "statusText": "Condo for sale",
      "isZillowOwned": false,
      "addressRaw": "137 Trellis Pl, Richardson, TX 75081",
      "streetAddress": "137 Trellis Pl",
      "city": "Richardson",
      "state": "TX",
      "zipcode": "75081",
      "rentZestimate": 1891,
      "bedrooms": 3,
      "bathrooms": 2,
      "livingArea": 1320,
      "lotAreaValue": 10.198,
      "homeType": "CONDO",
      "homeStatus": "FOR_SALE",
      "daysOnZillow": 16,
      "timeOnZillow": 1442733000,
      "latitude": 32.943813,
      "longitude": -96.684555,
      "isFeatured": false,
      "isPreforeclosureAuction": false,
      "country": "USA",
      "currency": "USD",
      "priceRaw": "$225,000"
    },
    {
      "zpid": "27179646",
      "price": 265000,
      "zestimate": 258000,
      "imgSrc": "https://photos.zillowstatic.com/fp/553f66c02ae5add63ecafea5e5099ef4-p_e.jpg",
      "detailUrl": "https://www.zillow.com/homedetails/501-Towne-House-Ln-Richardson-TX-75081/27179646_zpid/",
      "statusText": "Condo for sale",
      "isZillowOwned": false,
      "addressRaw": "501 Towne House Ln, Richardson, TX 75081",
      "streetAddress": "501 Towne House Ln",
      "city": "Richardson",
      "state": "TX",
      "zipcode": "75081",
      "rentZestimate": 2042,
      "taxAssessedValue": 258230,
      "bedrooms": 3,
      "bathrooms": 3,
      "livingArea": 1817,
      "lotAreaValue": 2744.28,
      "homeType": "CONDO",
      "homeStatus": "FOR_SALE",
      "daysOnZillow": 55,
      "timeOnZillow": 4816052000,
      "latitude": 32.942665,
      "longitude": -96.71489,
      "isFeatured": false,
      "isPreforeclosureAuction": false,
      "country": "USA",
      "currency": "USD",
      "priceRaw": "$265,000"
    },
    {
      "zpid": "27159727",
      "price": 479900,
      "zestimate": 477700,
      "imgSrc": "https://photos.zillowstatic.com/fp/fc1b24c8aeaf57e3903bc2753cdf078e-p_e.jpg",
      "detailUrl": "https://www.zillow.com/homedetails/1616-Aurora-Dr-Richardson-TX-75081/27159727_zpid/",
      "statusText": "House for sale",
      "isZillowOwned": false,
      "addressRaw": "1616 Aurora Dr, Richardson, TX 75081",
      "streetAddress": "1616 Aurora Dr",
      "city": "Richardson",
      "state": "TX",
      "zipcode": "75081",
      "rentZestimate": 2598,
      "taxAssessedValue": 382190,
      "bedrooms": 4,
      "bathrooms": 2,
      "livingArea": 1696,
      "lotAreaValue": 8973.36,
      "homeType": "SINGLE_FAMILY",
      "homeStatus": "FOR_SALE",
      "daysOnZillow": 79,
      "timeOnZillow": 6872729000,
      "latitude": 32.969097,
      "longitude": -96.69352,
      "priceChange": -30100,
      "datePriceChanged": 1766044800000,
      "isFeatured": false,
      "isPreforeclosureAuction": false,
      "country": "USA",
      "currency": "USD",
      "priceRaw": "$479,900"
    },
    {
      "zpid": "2063263189",
      "price": 215000,
      "zestimate": 212800,
      "imgSrc": "https://photos.zillowstatic.com/fp/7a5057095ca641da01620140d35f1316-p_e.jpg",
      "detailUrl": "https://www.zillow.com/homedetails/2323-Trellis-Pl-Richardson-TX-75081/2063263189_zpid/",
      "statusText": "Condo for sale",
      "isZillowOwned": false,
      "addressRaw": "2323 Trellis Pl, Richardson, TX 75081",
      "streetAddress": "2323 Trellis Pl",
      "city": "Richardson",
      "state": "TX",
      "zipcode": "75081",
      "rentZestimate": 1797,
      "bedrooms": 2,
      "bathrooms": 2,
      "livingArea": 1111,
      "lotAreaValue": 10.198,
      "homeType": "CONDO",
      "homeStatus": "FOR_SALE",
      "daysOnZillow": 7,
      "timeOnZillow": 651759000,
      "latitude": 32.943813,
      "longitude": -96.684555,
      "isFeatured": false,
      "isPreforeclosureAuction": false,
      "country": "USA",
      "currency": "USD",
      "priceRaw": "$215,000"
    },
    {
      "zpid": "27174385",
      "price": 198000,
      "zestimate": 210300,
      "imgSrc": "https://photos.zillowstatic.com/fp/152790c40f67b39d55a8ab4f4cd7474f-p_e.jpg",
      "detailUrl": "https://www.zillow.com/homedetails/2310-Village-North-Dr-2310-Richardson-TX-75081/27174385_zpid/",
      "statusText": "Townhouse for sale",
      "isZillowOwned": false,
      "addressRaw": "2310 Village North Dr #2310, Richardson, TX 75081",
      "streetAddress": "2310 Village North Dr #2310",
      "city": "Richardson",
      "state": "TX",
      "zipcode": "75081",
      "rentZestimate": 1571,
      "taxAssessedValue": 230550,
      "bedrooms": 1,
      "bathrooms": 3,
      "livingArea": 1314,
      "lotAreaValue": 10.198,
      "homeType": "TOWNHOUSE",
      "homeStatus": "FOR_SALE",
      "daysOnZillow": 17,
      "timeOnZillow": 1530089000,
      "latitude": 32.943813,
      "longitude": -96.684555,
      "priceChange": -21500,
      "datePriceChanged": 1771315200000,
      "isFeatured": false,
      "isPreforeclosureAuction": false,
      "country": "USA",
      "currency": "USD",
      "priceRaw": "$198,000"
    },
    {
      "zpid": "2070174935",
      "price": 255000,
      "zestimate": 246600,
      "imgSrc": "https://photos.zillowstatic.com/fp/e8bbc020daa481f01e5d65005ed3b14a-p_e.jpg",
      "detailUrl": "https://www.zillow.com/homedetails/2113-Trellis-Pl-Richardson-TX-75081/2070174935_zpid/",
      "statusText": "Townhouse for sale",
      "isZillowOwned": false,
      "addressRaw": "2113 Trellis Pl, Richardson, TX 75081",
      "streetAddress": "2113 Trellis Pl",
      "city": "Richardson",
      "state": "TX",
      "zipcode": "75081",
      "rentZestimate": 1737,
      "bedrooms": 3,
      "bathrooms": 2,
      "livingArea": 1320,
      "lotAreaValue": 10.198,
      "homeType": "TOWNHOUSE",
      "homeStatus": "FOR_SALE",
      "daysOnZillow": 23,
      "timeOnZillow": 2053105000,
      "latitude": 32.943813,
      "longitude": -96.684555,
      "isFeatured": false,
      "isPreforeclosureAuction": false,
      "country": "USA",
      "currency": "USD",
      "priceRaw": "$255,000"
    },
    {
      "zpid": "457468353",
      "price": 243900,
      "zestimate": 240000,
      "imgSrc": "https://photos.zillowstatic.com/fp/2fc59cf32715b1678efda2b6669afa52-p_e.jpg",
      "detailUrl": "https://www.zillow.com/homedetails/2330-Village-North-Dr-Richardson-TX-75081/457468353_zpid/",
      "statusText": "Townhouse for sale",
      "isZillowOwned": false,
      "addressRaw": "2330 Village North Dr, Richardson, TX 75081",
      "streetAddress": "2330 Village North Dr",
      "city": "Richardson",
      "state": "TX",
      "zipcode": "75081",
      "rentZestimate": 1791,
      "bedrooms": 3,
      "bathrooms": 3,
      "livingArea": 1314,
      "lotAreaValue": 10.198,
      "homeType": "TOWNHOUSE",
      "homeStatus": "FOR_SALE",
      "daysOnZillow": 126,
      "timeOnZillow": 10917560000,
      "latitude": 32.943813,
      "longitude": -96.684555,
      "priceChange": -1100,
      "datePriceChanged": 1769587200000,
      "isFeatured": false,
      "isPreforeclosureAuction": false,
      "country": "USA",
      "currency": "USD",
      "priceRaw": "$243,900"
    },
    {
      "zpid": "450244882",
      "price": 240000,
      "zestimate": 235900,
      "imgSrc": "https://photos.zillowstatic.com/fp/f90a4688dcf1fcd6e4dcb636ccac04d2-p_e.jpg",
      "detailUrl": "https://www.zillow.com/homedetails/145-Trellis-Pl-Richardson-TX-75081/450244882_zpid/",
      "statusText": "Condo for sale",
      "isZillowOwned": false,
      "addressRaw": "145 Trellis Pl, Richardson, TX 75081",
      "streetAddress": "145 Trellis Pl",
      "city": "Richardson",
      "state": "TX",
      "zipcode": "75081",
      "rentZestimate": 1737,
      "bedrooms": 3,
      "bathrooms": 2,
      "livingArea": 1320,
      "lotAreaValue": 10.198,
      "homeType": "CONDO",
      "homeStatus": "FOR_SALE",
      "daysOnZillow": 76,
      "timeOnZillow": 6632439000,
      "latitude": 32.943813,
      "longitude": -96.684555,
      "isFeatured": false,
      "isPreforeclosureAuction": false,
      "country": "USA",
      "currency": "USD",
      "priceRaw": "$240,000"
    },
    {
      "zpid": "27179668",
      "price": 249000,
      "zestimate": 241900,
      "imgSrc": "https://photos.zillowstatic.com/fp/1970decd70f69350ca1230ef83d15da2-p_e.jpg",
      "detailUrl": "https://www.zillow.com/homedetails/323-Towne-House-Ln-Richardson-TX-75081/27179668_zpid/",
      "statusText": "Townhouse for sale",
      "isZillowOwned": false,
      "addressRaw": "323 Towne House Ln, Richardson, TX 75081",
      "streetAddress": "323 Towne House Ln",
      "city": "Richardson",
      "state": "TX",
      "zipcode": "75081",
      "rentZestimate": 1958,
      "taxAssessedValue": 233610,
      "bedrooms": 2,
      "bathrooms": 2,
      "livingArea": 1224,
      "lotAreaValue": 4007.52,
      "homeType": "TOWNHOUSE",
      "homeStatus": "FOR_SALE",
      "daysOnZillow": 35,
      "timeOnZillow": 3093690000,
      "latitude": 32.944595,
      "longitude": -96.71512,
      "isFeatured": false,
      "isPreforeclosureAuction": false,
      "country": "USA",
      "currency": "USD",
      "priceRaw": "$249,000"
    },
    {
      "zpid": "456782031",
      "price": 430000,
      "zestimate": 416400,
      "imgSrc": "https://photos.zillowstatic.com/fp/5de9c2b211b3c8d8cca0acc956271f74-p_e.jpg",
      "detailUrl": "https://www.zillow.com/homedetails/620-622-Royal-Crest-Dr-Richardson-TX-75081/456782031_zpid/",
      "statusText": "House for sale",
      "isZillowOwned": false,
      "addressRaw": "620-622 Royal Crest Dr, Richardson, TX 75081",
      "streetAddress": "620-622 Royal Crest Dr",
      "city": "Richardson",
      "state": "TX",
      "zipcode": "75081",
      "rentZestimate": 2001,
      "bedrooms": 3,
      "bathrooms": 2,
      "livingArea": 1382,
      "lotAreaValue": 7623,
      "homeType": "SINGLE_FAMILY",
      "homeStatus": "FOR_SALE",
      "daysOnZillow": 17,
      "timeOnZillow": 1546895000,
      "latitude": 32.95386,
      "longitude": -96.7163,
      "isFeatured": false,
      "isPreforeclosureAuction": false,
      "country": "USA",
      "currency": "USD",
      "priceRaw": "$430,000"
    },
    {
      "zpid": "27165183",
      "price": 325000,
      "imgSrc": "https://photos.zillowstatic.com/fp/80eaca1e964910e4643cc3cfa2ab13b8-p_e.jpg",
      "detailUrl": "https://www.zillow.com/homedetails/407-Maple-St-Richardson-TX-75081/27165183_zpid/",
      "statusText": "Lot / Land for sale",
      "isZillowOwned": false,
      "addressRaw": "407 Maple St, Richardson, TX 75081",
      "streetAddress": "407 Maple St",
      "city": "Richardson",
      "state": "TX",
      "zipcode": "75081",
      "taxAssessedValue": 150000,
      "lotAreaValue": 0.25,
      "homeType": "LOT",
      "homeStatus": "FOR_SALE",
      "daysOnZillow": 8,
      "timeOnZillow": 766463000,
      "latitude": 32.941875,
      "longitude": -96.72846,
      "isFeatured": false,
      "isPreforeclosureAuction": false,
      "country": "USA",
      "currency": "USD",
      "priceRaw": "$325,000"
    },
    {
      "zpid": "27165149",
      "price": 375000,
      "imgSrc": "https://photos.zillowstatic.com/fp/ecb71d0765831026aafb5babd8020908-p_e.jpg",
      "detailUrl": "https://www.zillow.com/homedetails/439-Pittman-St-Richardson-TX-75081/27165149_zpid/",
      "statusText": "Lot / Land for sale",
      "isZillowOwned": false,
      "addressRaw": "439 Pittman St, Richardson, TX 75081",
      "streetAddress": "439 Pittman St",
      "city": "Richardson",
      "state": "TX",
      "zipcode": "75081",
      "rentZestimate": 2477,
      "taxAssessedValue": 150000,
      "lotAreaValue": 0.27599999999999997,
      "homeType": "LOT",
      "homeStatus": "FOR_SALE",
      "daysOnZillow": 182,
      "timeOnZillow": 15779374000,
      "latitude": 32.9429,
      "longitude": -96.727394,
      "priceChange": -10000,
      "datePriceChanged": 1759906800000,
      "isFeatured": false,
      "isPreforeclosureAuction": false,
      "country": "USA",
      "currency": "USD",
      "priceRaw": "$375,000"
    }
  ]
}